{"ranking": [{"change": "-0.5", "changePercent": "-0.35%", "dayHigh": "149.0", "dayHighLimitDown": false, "dayHighLimitUp": false, "dayHighLowDiff": "6.50", "dayLow": "142.5", "dayLowLimitDown": false, "dayLowLimitUp": false, "limitDown": false, "limitUp": false, "name": "\u9577\u69ae", "previousClose": "144.0", "price": "143.5", "rank": "1", "symbol": "2603.TW", "turnoverK": "34287364", "volume": "234775000", "previousLimitUp": false, "previousLimitDown": false, "previousChange": null, "previousChangePercent": null, "holdK": null, "holdPercent": null, "overboughtK": null, "oversoldK": null, "boughtK": null, "soldK": null, "regularMarketDayHigh": "149.0", "regularMarketDayLow": "142.5", "rowId": "2603.TW", "symbolName": "\u9577\u69ae", "volK": 234775, "prevRank": "1", "inRankCount": 133}, {"change": "6.0", "changePercent": "+3.14%", "dayHigh": "203.0", "dayHighLimitDown": false, "dayHighLimitUp": false, "dayHighLowDiff": "11.00", "dayLow": "192.0", "dayLowLimitDown": false, "dayLowLimitUp": false, "limitDown": false, "limitUp": false, "name": "\u842c\u6d77", "previousClose": "191.0", "price": "197.0", "rank": "2", "symbol": "2615.TW", "turnoverK": "20721248", "volume": "104587000", "previousLimitUp": false, "previousLimitDown": false, "previousChange": null, "previousChangePercent": null, "holdK": null, "holdPercent": null, "overboughtK": null, "oversoldK": null, "boughtK": null, "soldK": null, "regularMarketDayHigh": "203.0", "regularMarketDayLow": "192.0", "rowId": "2615.TW", "symbolName": "\u842c\u6d77", "volK": 104587, "prevRank": "2", "inRankCount": 133}, {"change": "0.5", "changePercent": "+0.4%", "dayHigh": "131.5", "dayHighLimitDown": false, "dayHighLimitUp": false, "dayHighLowDiff": "6.50", "dayLow": "125.0", "dayLowLimitDown": false, "dayLowLimitUp": false, "limitDown": false, "limitUp": false, "name": "\u967d\u660e", "previousClose": "126.5", "price": "127.0", "rank": "3", "symbol": "2609.TW", "turnoverK": "17042866", "volume": "132493000", "previousLimitUp": false, "previousLimitDown": false, "previousChange": null, "previousChangePercent": null, "holdK": null, "holdPercent": null, "overboughtK": null, "oversoldK": null, "boughtK": null, "soldK": null, "regularMarketDayHigh": "131.5", "regularMarketDayLow": "125.0", "rowId": "2609.TW", "symbolName": "\u967d\u660e", "volK": 132493, "prevRank": "3", "inRankCount": 133}, {"change": "0.10", "changePercent": "+0.35%", "dayHigh": "28.75", "dayHighLimitDown": false, "dayHighLimitUp": false, "dayHighLowDiff": "1.20", "dayLow": "27.55", "dayLowLimitDown": false, "dayLowLimitUp": false, "limitDown": false, "limitUp": false, "name": "\u83ef\u822a", "previousClose": "28.40", "price": "28.50", "rank": "4", "symbol": "2610.TW", "turnoverK": "15101082", "volume": "533909000", "previousLimitUp": false, "previousLimitDown": false, "previousChange": null, "previousChangePercent": null, "holdK": null, "holdPercent": null, "overboughtK": null, "oversoldK": null, "boughtK": null, "soldK": null, "regularMarketDayHigh": "28.75", "regularMarketDayLow": "27.55", "rowId": "2610.TW", "symbolName": "\u83ef\u822a", "volK": 533909, "prevRank": "4", "inRankCount": 30}, {"change": "-5", "changePercent": "-0.82%", "dayHigh": "614", "dayHighLimitDown": false, "dayHighLimitUp": false, "dayHighLowDiff": "12.00", "dayLow": "602", "dayLowLimitDown": false, "dayLowLimitUp": false, "limitDown": false, "limitUp": false, "name": "\u53f0\u7a4d\u96fb", "previousClose": "607", "price": "602", "rank": "5", "symbol": "2330.TW", "turnoverK": "12569463", "volume": "20673000", "previousLimitUp": false, "previousLimitDown": false, "previousChange": null, "previousChangePercent": null, "holdK": null, "holdPercent": null, "overboughtK": null, "oversoldK": null, "boughtK": null, "soldK": null, "regularMarketDayHigh": "614", "regularMarketDayLow": "602", "rowId": "2330.TW", "symbolName": "\u53f0\u7a4d\u96fb", "volK": 20673, "prevRank": "5", "inRankCount": 133}, {"change": "0.0", "changePercent": "0%", "dayHigh": "68.2", "dayHighLimitDown": false, "dayHighLimitUp": false, "dayHighLowDiff": "1.70", "dayLow": "66.5", "dayLowLimitDown": false, "dayLowLimitUp": false, "limitDown": false, "limitUp": false, "name": "\u806f\u96fb", "previousClose": "66.5", "price": "66.5", "rank": "6", "symbol": "2303.TW", "turnoverK": "9694886", "volume": "143818000", "previousLimitUp": false, "previousLimitDown": false, "previousChange": null, "previousChangePercent": null, "holdK": null, "holdPercent": null, "overboughtK": null, "oversoldK": null, "boughtK": null, "soldK": null, "regularMarketDayHigh": "68.2", "regularMarketDayLow": "66.5", "rowId": "2303.TW", "symbolName": "\u806f\u96fb", "volK": 143818, "prevRank": "7", "inRankCount": 133}, {"change": "0.75", "changePercent": "+2.69%", "dayHigh": "28.95", "dayHighLimitDown": false, "dayHighLimitUp": false, "dayHighLowDiff": "1.75", "dayLow": "27.20", "dayLowLimitDown": false, "dayLowLimitUp": false, "limitDown": false, "limitUp": false, "name": "\u9577\u69ae\u822a", "previousClose": "27.90", "price": "28.65", "rank": "7", "symbol": "2618.TW", "turnoverK": "8998789", "volume": "318610000", "previousLimitUp": false, "previousLimitDown": false, "previousChange": null, "previousChangePercent": null, "holdK": null, "holdPercent": null, "overboughtK": null, "oversoldK": null, "boughtK": null, "soldK": null, "regularMarketDayHigh": "28.95", "regularMarketDayLow": "27.20", "rowId": "2618.TW", "symbolName": "\u9577\u69ae\u822a", "volK": 318610, "prevRank": "9", "inRankCount": 30}, {"change": "30", "changePercent": "+2.82%", "dayHigh": "1110", "dayHighLimitDown": false, "dayHighLimitUp": false, "dayHighLowDiff": "30.00", "dayLow": "1080", "dayLowLimitDown": false, "dayLowLimitUp": false, "limitDown": false, "limitUp": false, "name": "\u806f\u767c\u79d1", "previousClose": "1065", "price": "1095", "rank": "8", "symbol": "2454.TW", "turnoverK": "7995800", "volume": "7313000", "previousLimitUp": false, "previousLimitDown": false, "previousChange": null, "previousChangePercent": null, "holdK": null, "holdPercent": null, "overboughtK": null, "oversoldK": null, "boughtK": null, "soldK": null, "regularMarketDayHigh": "1110", "regularMarketDayLow": "1080", "rowId": "2454.TW", "symbolName": "\u806f\u767c\u79d1", "volK": 7313, "prevRank": "11", "inRankCount": 133}, {"change": "17.5", "changePercent": "+9.89%", "dayHigh": "194.5", "dayHighLimitDown": false, "dayHighLimitUp": true, "dayHighLowDiff": "14.00", "dayLow": "180.5", "dayLowLimitDown": false, "dayLowLimitUp": false, "limitDown": false, "limitUp": true, "name": "\u667a\u539f", "previousClose": "177.0", "price": "194.5", "rank": "9", "symbol": "3035.TW", "turnoverK": "7063399", "volume": "37399000", "previousLimitUp": false, "previousLimitDown": false, "previousChange": null, "previousChangePercent": null, "holdK": null, "holdPercent": null, "overboughtK": null, "oversoldK": null, "boughtK": null, "soldK": null, "regularMarketDayHigh": "194.5", "regularMarketDayLow": "180.5", "rowId": "3035.TW", "symbolName": "\u667a\u539f", "volK": 37399, "prevRank": "29", "inRankCount": 91}, {"change": "-2.7", "changePercent": "-3.21%", "dayHigh": "86.8", "dayHighLimitDown": false, "dayHighLimitUp": false, "dayHighLowDiff": "5.70", "dayLow": "81.1", "dayLowLimitDown": false, "dayLowLimitUp": false, "limitDown": false, "limitUp": false, "name": "\u5b8f\u9054\u96fb", "previousClose": "84.0", "price": "81.3", "rank": "10", "symbol": "2498.TW", "turnoverK": "6613262", "volume": "78728000", "previousLimitUp": false, "previousLimitDown": false, "previousChange": null, "previousChangePercent": null, "holdK": null, "holdPercent": null, "overboughtK": null, "oversoldK": null, "boughtK": null, "soldK": null, "regularMarketDayHigh": "86.8", "regularMarketDayLow": "81.1", "rowId": "2498.TW", "symbolName": "\u5b8f\u9054\u96fb", "volK": 78728, "prevRank": "6", "inRankCount": 38}, {"change": "4.5", "changePercent": "+2.08%", "dayHigh": "225.0", "dayHighLimitDown": false, "dayHighLimitUp": false, "dayHighLowDiff": "6.00", "dayLow": "219.0", "dayLowLimitDown": false, "dayLowLimitUp": false, "limitDown": false, "limitUp": false, "name": "\u6b23\u8208", "previousClose": "216.5", "price": "221.0", "rank": "11", "symbol": "3037.TW", "turnoverK": "5827050", "volume": "26183000", "previousLimitUp": false, "previousLimitDown": false, "previousChange": null, "previousChangePercent": null, "holdK": null, "holdPercent": null, "overboughtK": null, "oversoldK": null, "boughtK": null, "soldK": null, "regularMarketDayHigh": "225.0", "regularMarketDayLow": "219.0", "rowId": "3037.TW", "symbolName": "\u6b23\u8208", "volK": 26183, "prevRank": "10", "inRankCount": 133}, {"change": "6", "changePercent": "+1.17%", "dayHigh": "525", "dayHighLimitDown": false, "dayHighLimitUp": false, "dayHighLowDiff": "10.00", "dayLow": "515", "dayLowLimitDown": false, "dayLowLimitUp": false, "limitDown": false, "limitUp": false, "name": "\u806f\u8a60", "previousClose": "513", "price": "519", "rank": "12", "symbol": "3034.TW", "turnoverK": "4801318", "volume": "9239000", "previousLimitUp": false, "previousLimitDown": false, "previousChange": null, "previousChangePercent": null, "holdK": null, "holdPercent": null, "overboughtK": null, "oversoldK": null, "boughtK": null, "soldK": null, "regularMarketDayHigh": "525", "regularMarketDayLow": "515", "rowId": "3034.TW", "symbolName": "\u806f\u8a60", "volK": 9239, "prevRank": "14", "inRankCount": 133}, {"change": "10.0", "changePercent": "+7.55%", "dayHigh": "143.5", "dayHighLimitDown": false, "dayHighLimitUp": false, "dayHighLowDiff": "8.50", "dayLow": "135.0", "dayLowLimitDown": false, "dayLowLimitUp": false, "limitDown": false, "limitUp": false, "name": "\u6280\u5609", "previousClose": "132.5", "price": "142.5", "rank": "13", "symbol": "2376.TW", "turnoverK": "4759040", "volume": "34018000", "previousLimitUp": false, "previousLimitDown": false, "previousChange": null, "previousChangePercent": null, "holdK": null, "holdPercent": null, "overboughtK": null, "oversoldK": null, "boughtK": null, "soldK": null, "regularMarketDayHigh": "143.5", "regularMarketDayLow": "135.0", "rowId": "2376.TW", "symbolName": "\u6280\u5609", "volK": 34018, "prevRank": "41", "inRankCount": 44}, {"change": "5.0", "changePercent": "+4.67%", "dayHigh": "114.0", "dayHighLimitDown": false, "dayHighLimitUp": false, "dayHighLowDiff": "5.50", "dayLow": "108.5", "dayLowLimitDown": false, "dayLowLimitUp": false, "limitDown": false, "limitUp": false, "name": "\u5149\u7f69", "previousClose": "107.0", "price": "112.0", "rank": "14", "symbol": "2338.TW", "turnoverK": "3937015", "volume": "35458000", "previousLimitUp": false, "previousLimitDown": false, "previousChange": null, "previousChangePercent": null, "holdK": null, "holdPercent": null, "overboughtK": null, "oversoldK": null, "boughtK": null, "soldK": null, "regularMarketDayHigh": "114.0", "regularMarketDayLow": "108.5", "rowId": "2338.TW", "symbolName": "\u5149\u7f69", "volK": 35458, "prevRank": "8", "inRankCount": 28}, {"change": "-1.0", "changePercent": "-0.94%", "dayHigh": "107.0", "dayHighLimitDown": false, "dayHighLimitUp": false, "dayHighLowDiff": "2.00", "dayLow": "105.0", "dayLowLimitDown": false, "dayLowLimitUp": false, "limitDown": false, "limitUp": false, "name": "\u9d3b\u6d77", "previousClose": "106.0", "price": "105.0", "rank": "15", "symbol": "2317.TW", "turnoverK": "3706728", "volume": "35027000", "previousLimitUp": false, "previousLimitDown": false, "previousChange": null, "previousChangePercent": null, "holdK": null, "holdPercent": null, "overboughtK": null, "oversoldK": null, "boughtK": null, "soldK": null, "regularMarketDayHigh": "107.0", "regularMarketDayLow": "105.0", "rowId": "2317.TW", "symbolName": "\u9d3b\u6d77", "volK": 35027, "prevRank": "26", "inRankCount": 133}, {"change": "-0.10", "changePercent": "-0.53%", "dayHigh": "19.20", "dayHighLimitDown": false, "dayHighLimitUp": false, "dayHighLowDiff": "0.55", "dayLow": "18.65", "dayLowLimitDown": false, "dayLowLimitUp": false, "limitDown": false, "limitUp": false, "name": "\u7fa4\u5275", "previousClose": "18.95", "price": "18.85", "rank": "16", "symbol": "3481.TW", "turnoverK": "3454101", "volume": "182090000", "previousLimitUp": false, "previousLimitDown": false, "previousChange": null, "previousChangePercent": null, "holdK": null, "holdPercent": null, "overboughtK": null, "oversoldK": null, "boughtK": null, "soldK": null, "regularMarketDayHigh": "19.20", "regularMarketDayLow": "18.65", "rowId": "3481.TW", "symbolName": "\u7fa4\u5275", "volK": 182090, "prevRank": "12", "inRankCount": 133}, {"change": "180", "changePercent": "+4.28%", "dayHigh": "4455", "dayHighLimitDown": false, "dayHighLimitUp": false, "dayHighLowDiff": "150.00", "dayLow": "4305", "dayLowLimitDown": false, "dayLowLimitUp": false, "limitDown": false, "limitUp": false, "name": "\u77fd\u529b-KY", "previousClose": "4205", "price": "4385", "rank": "17", "symbol": "6415.TW", "turnoverK": "3260070", "volume": "744000", "previousLimitUp": false, "previousLimitDown": false, "previousChange": null, "previousChangePercent": null, "holdK": null, "holdPercent": null, "overboughtK": null, "oversoldK": null, "boughtK": null, "soldK": null, "regularMarketDayHigh": "4455", "regularMarketDayLow": "4305", "rowId": "6415.TW", "symbolName": "\u77fd\u529b-KY", "volK": 744, "prevRank": "22", "inRankCount": 20}, {"change": "26.0", "changePercent": "+9.98%", "dayHigh": "286.5", "dayHighLimitDown": false, "dayHighLimitUp": true, "dayHighLowDiff": "31.00", "dayLow": "255.5", "dayLowLimitDown": false, "dayLowLimitUp": false, "limitDown": false, "limitUp": true, "name": "\u83ef\u64ce", "previousClose": "260.5", "price": "286.5", "rank": "18", "symbol": "3515.TW", "turnoverK": "3135071", "volume": "11569000", "previousLimitUp": false, "previousLimitDown": false, "previousChange": null, "previousChangePercent": null, "holdK": null, "holdPercent": null, "overboughtK": null, "oversoldK": null, "boughtK": null, "soldK": null, "regularMarketDayHigh": "286.5", "regularMarketDayLow": "255.5", "rowId": "3515.TW", "symbolName": "\u83ef\u64ce", "volK": 11569, "prevRank": "50", "inRankCount": 10}, {"change": "0.00", "changePercent": "0%", "dayHigh": "22.20", "dayHighLimitDown": false, "dayHighLimitUp": false, "dayHighLowDiff": "0.50", "dayLow": "21.70", "dayLowLimitDown": false, "dayLowLimitUp": false, "limitDown": false, "limitUp": false, "name": "\u53cb\u9054", "previousClose": "21.90", "price": "21.90", "rank": "19", "symbol": "2409.TW", "turnoverK": "2987176", "volume": "135853000", "previousLimitUp": false, "previousLimitDown": false, "previousChange": null, "previousChangePercent": null, "holdK": null, "holdPercent": null, "overboughtK": null, "oversoldK": null, "boughtK": null, "soldK": null, "regularMarketDayHigh": "22.20", "regularMarketDayLow": "21.70", "rowId": "2409.TW", "symbolName": "\u53cb\u9054", "volK": 135853, "prevRank": "19", "inRankCount": 133}, {"change": "27.0", "changePercent": "+9.96%", "dayHigh": "298.0", "dayHighLimitDown": false, "dayHighLimitUp": true, "dayHighLowDiff": "28.00", "dayLow": "270.0", "dayLowLimitDown": false, "dayLowLimitUp": false, "limitDown": false, "limitUp": true, "name": "\u53f0\u52dd\u79d1", "previousClose": "271.0", "price": "298.0", "rank": "20", "symbol": "3532.TW", "turnoverK": "2968750", "volume": "10295000", "previousLimitUp": false, "previousLimitDown": false, "previousChange": null, "previousChangePercent": null, "holdK": null, "holdPercent": null, "overboughtK": null, "oversoldK": null, "boughtK": null, "soldK": null, "regularMarketDayHigh": "298.0", "regularMarketDayLow": "270.0", "rowId": "3532.TW", "symbolName": "\u53f0\u52dd\u79d1", "volK": 10295, "prevRank": "59", "inRankCount": 13}, {"change": "0.15", "changePercent": "+0.38%", "dayHigh": "41.00", "dayHighLimitDown": false, "dayHighLimitUp": false, "dayHighLowDiff": "2.00", "dayLow": "39.00", "dayLowLimitDown": false, "dayLowLimitUp": false, "limitDown": false, "limitUp": false, "name": "\u4e2d\u9d3b", "previousClose": "39.00", "price": "39.15", "rank": "21", "symbol": "2014.TW", "turnoverK": "2795954", "volume": "70233000", "previousLimitUp": false, "previousLimitDown": false, "previousChange": null, "previousChangePercent": null, "holdK": null, "holdPercent": null, "overboughtK": null, "oversoldK": null, "boughtK": null, "soldK": null, "regularMarketDayHigh": "41.00", "regularMarketDayLow": "39.00", "rowId": "2014.TW", "symbolName": "\u4e2d\u9d3b", "volK": 70233, "prevRank": "37", "inRankCount": 5}, {"change": "-0.15", "changePercent": "-0.37%", "dayHigh": "41.95", "dayHighLimitDown": false, "dayHighLimitUp": false, "dayHighLowDiff": "1.85", "dayLow": "40.10", "dayLowLimitDown": false, "dayLowLimitUp": false, "limitDown": false, "limitUp": false, "name": "\u5143\u6676", "previousClose": "41.00", "price": "40.85", "rank": "22", "symbol": "6443.TW", "turnoverK": "2556382", "volume": "62275000", "previousLimitUp": false, "previousLimitDown": false, "previousChange": null, "previousChangePercent": null, "holdK": null, "holdPercent": null, "overboughtK": null, "oversoldK": null, "boughtK": null, "soldK": null, "regularMarketDayHigh": "41.95", "regularMarketDayLow": "40.10", "rowId": "6443.TW", "symbolName": "\u5143\u6676", "volK": 62275, "prevRank": "15", "inRankCount": 6}, {"change": "-26", "changePercent": "-4.68%", "dayHigh": "576", "dayHighLimitDown": false, "dayHighLimitUp": false, "dayHighLowDiff": "48.00", "dayLow": "528", "dayLowLimitDown": false, "dayLowLimitUp": false, "limitDown": false, "limitUp": false, "name": "\u5a01\u92d2\u96fb\u5b50", "previousClose": "555", "price": "529", "rank": "23", "symbol": "6756.TW", "turnoverK": "2552095", "volume": "4637000", "previousLimitUp": false, "previousLimitDown": false, "previousChange": null, "previousChangePercent": null, "holdK": null, "holdPercent": null, "overboughtK": null, "oversoldK": null, "boughtK": null, "soldK": null, "regularMarketDayHigh": "576", "regularMarketDayLow": "528", "rowId": "6756.TW", "symbolName": "\u5a01\u92d2\u96fb\u5b50", "volK": 4637, "prevRank": "39", "inRankCount": 37}, {"change": "-0.35", "changePercent": "-0.73%", "dayHigh": "49.50", "dayHighLimitDown": false, "dayHighLimitUp": false, "dayHighLowDiff": "1.90", "dayLow": "47.60", "dayLowLimitDown": false, "dayLowLimitUp": false, "limitDown": false, "limitUp": false, "name": "\u5927\u6210\u92fc", "previousClose": "47.95", "price": "47.60", "rank": "24", "symbol": "2027.TW", "turnoverK": "2459473", "volume": "50950000", "previousLimitUp": false, "previousLimitDown": false, "previousChange": null, "previousChangePercent": null, "holdK": null, "holdPercent": null, "overboughtK": null, "oversoldK": null, "boughtK": null, "soldK": null, "regularMarketDayHigh": "49.50", "regularMarketDayLow": "47.60", "rowId": "2027.TW", "symbolName": "\u5927\u6210\u92fc", "volK": 50950, "prevRank": "35", "inRankCount": 23}, {"change": "9.0", "changePercent": "+3.95%", "dayHigh": "238.0", "dayHighLimitDown": false, "dayHighLimitUp": false, "dayHighLowDiff": "6.00", "dayLow": "232.0", "dayLowLimitDown": false, "dayLowLimitUp": false, "limitDown": false, "limitUp": false, "name": "\u666f\u78a9", "previousClose": "228.0", "price": "237.0", "rank": "25", "symbol": "3189.TW", "turnoverK": "2401116", "volume": "10194000", "previousLimitUp": false, "previousLimitDown": false, "previousChange": null, "previousChangePercent": null, "holdK": null, "holdPercent": null, "overboughtK": null, "oversoldK": null, "boughtK": null, "soldK": null, "regularMarketDayHigh": "238.0", "regularMarketDayLow": "232.0", "rowId": "3189.TW", "symbolName": "\u666f\u78a9", "volK": 10194, "prevRank": "23", "inRankCount": 112}, {"change": "0.5", "changePercent": "+0.35%", "dayHigh": "147.0", "dayHighLimitDown": false, "dayHighLimitUp": false, "dayHighLowDiff": "6.00", "dayLow": "141.0", "dayLowLimitDown": false, "dayLowLimitUp": false, "limitDown": false, "limitUp": false, "name": "\u65b0\u5510", "previousClose": "144.0", "price": "144.5", "rank": "26", "symbol": "4919.TW", "turnoverK": "2386056", "volume": "16551000", "previousLimitUp": false, "previousLimitDown": false, "previousChange": null, "previousChangePercent": null, "holdK": null, "holdPercent": null, "overboughtK": null, "oversoldK": null, "boughtK": null, "soldK": null, "regularMarketDayHigh": "147.0", "regularMarketDayLow": "141.0", "rowId": "4919.TW", "symbolName": "\u65b0\u5510", "volK": 16551, "prevRank": "18", "inRankCount": 110}, {"change": "-1", "changePercent": "-0.17%", "dayHigh": "601", "dayHighLimitDown": false, "dayHighLimitUp": false, "dayHighLowDiff": "16.00", "dayLow": "585", "dayLowLimitDown": false, "dayLowLimitUp": false, "limitDown": false, "limitUp": false, "name": "\u5357\u96fb", "previousClose": "586", "price": "585", "rank": "27", "symbol": "8046.TW", "turnoverK": "2366274", "volume": "3983000", "previousLimitUp": false, "previousLimitDown": false, "previousChange": null, "previousChangePercent": null, "holdK": null, "holdPercent": null, "overboughtK": null, "oversoldK": null, "boughtK": null, "soldK": null, "regularMarketDayHigh": "601", "regularMarketDayLow": "585", "rowId": "8046.TW", "symbolName": "\u5357\u96fb", "volK": 3983, "prevRank": "25", "inRankCount": 133}, {"change": "19", "changePercent": "+3.65%", "dayHigh": "541", "dayHighLimitDown": false, "dayHighLimitUp": false, "dayHighLowDiff": "19.00", "dayLow": "522", "dayLowLimitDown": false, "dayLowLimitUp": false, "limitDown": false, "limitUp": false, "name": "\u7389\u6676\u5149", "previousClose": "520", "price": "539", "rank": "28", "symbol": "3406.TW", "turnoverK": "2358861", "volume": "4432000", "previousLimitUp": false, "previousLimitDown": false, "previousChange": null, "previousChangePercent": null, "holdK": null, "holdPercent": null, "overboughtK": null, "oversoldK": null, "boughtK": null, "soldK": null, "regularMarketDayHigh": "541", "regularMarketDayLow": "522", "rowId": "3406.TW", "symbolName": "\u7389\u6676\u5149", "volK": 4432, "prevRank": "48", "inRankCount": 19}, {"change": "-0.9", "changePercent": "-1.22%", "dayHigh": "75.0", "dayHighLimitDown": false, "dayHighLimitUp": false, "dayHighLowDiff": "2.40", "dayLow": "72.6", "dayLowLimitDown": false, "dayLowLimitUp": false, "limitDown": false, "limitUp": false, "name": "\u529b\u7a4d\u96fb", "previousClose": "73.6", "price": "72.7", "rank": "29", "symbol": "6770.TW", "turnoverK": "2309380", "volume": "31401000", "previousLimitUp": false, "previousLimitDown": false, "previousChange": null, "previousChangePercent": null, "holdK": null, "holdPercent": null, "overboughtK": null, "oversoldK": null, "boughtK": null, "soldK": null, "regularMarketDayHigh": "75.0", "regularMarketDayLow": "72.6", "rowId": "6770.TW", "symbolName": "\u529b\u7a4d\u96fb", "volK": 31401, "prevRank": "20", "inRankCount": 3}, {"change": "4.4", "changePercent": "+9.61%", "dayHigh": "50.3", "dayHighLimitDown": false, "dayHighLimitUp": true, "dayHighLowDiff": "2.00", "dayLow": "48.30", "dayLowLimitDown": false, "dayLowLimitUp": false, "limitDown": false, "limitUp": false, "name": "\u56db\u7dad\u822a", "previousClose": "45.80", "price": "50.2", "rank": "30", "symbol": "5608.TW", "turnoverK": "2285966", "volume": "45725000", "previousLimitUp": false, "previousLimitDown": false, "previousChange": null, "previousChangePercent": null, "holdK": null, "holdPercent": null, "overboughtK": null, "oversoldK": null, "boughtK": null, "soldK": null, "regularMarketDayHigh": "50.3", "regularMarketDayLow": "48.30", "rowId": "5608.TW", "symbolName": "\u56db\u7dad\u822a", "volK": 45725, "prevRank": "92", "inRankCount": 5}, {"change": "1.5", "changePercent": "+0.56%", "dayHigh": "276.0", "dayHighLimitDown": false, "dayHighLimitUp": false, "dayHighLowDiff": "8.50", "dayLow": "267.5", "dayLowLimitDown": false, "dayLowLimitUp": false, "limitDown": false, "limitUp": false, "name": "\u5929\u923a", "previousClose": "267.0", "price": "268.5", "rank": "31", "symbol": "4961.TW", "turnoverK": "2018507", "volume": "7456000", "previousLimitUp": false, "previousLimitDown": false, "previousChange": null, "previousChangePercent": null, "holdK": null, "holdPercent": null, "overboughtK": null, "oversoldK": null, "boughtK": null, "soldK": null, "regularMarketDayHigh": "276.0", "regularMarketDayLow": "267.5", "rowId": "4961.TW", "symbolName": "\u5929\u923a", "volK": 7456, "prevRank": "13", "inRankCount": 133}, {"change": "-1.2", "changePercent": "-1.33%", "dayHigh": "93.6", "dayHighLimitDown": false, "dayHighLimitUp": false, "dayHighLowDiff": "5.60", "dayLow": "88.0", "dayLowLimitDown": false, "dayLowLimitUp": false, "limitDown": false, "limitUp": false, "name": "\u5a01\u76db", "previousClose": "90.2", "price": "89.0", "rank": "32", "symbol": "2388.TW", "turnoverK": "1943956", "volume": "21344000", "previousLimitUp": false, "previousLimitDown": false, "previousChange": null, "previousChangePercent": null, "holdK": null, "holdPercent": null, "overboughtK": null, "oversoldK": null, "boughtK": null, "soldK": null, "regularMarketDayHigh": "93.6", "regularMarketDayLow": "88.0", "rowId": "2388.TW", "symbolName": "\u5a01\u76db", "volK": 21344, "prevRank": "17", "inRankCount": 35}, {"change": "3.0", "changePercent": "+2.88%", "dayHigh": "109.0", "dayHighLimitDown": false, "dayHighLimitUp": false, "dayHighLowDiff": "3.00", "dayLow": "106.0", "dayLowLimitDown": false, "dayLowLimitUp": false, "limitDown": false, "limitUp": false, "name": "\u65e5\u6708\u5149\u6295\u63a7", "previousClose": "104.0", "price": "107.0", "rank": "33", "symbol": "3711.TW", "turnoverK": "1908421", "volume": "17783000", "previousLimitUp": false, "previousLimitDown": false, "previousChange": null, "previousChangePercent": null, "holdK": null, "holdPercent": null, "overboughtK": null, "oversoldK": null, "boughtK": null, "soldK": null, "regularMarketDayHigh": "109.0", "regularMarketDayLow": "106.0", "rowId": "3711.TW", "symbolName": "\u65e5\u6708\u5149\u6295\u63a7", "volK": 17783, "prevRank": "44", "inRankCount": 92}, {"change": "-2.3", "changePercent": "-4.14%", "dayHigh": "57.0", "dayHighLimitDown": false, "dayHighLimitUp": false, "dayHighLowDiff": "4.00", "dayLow": "53.0", "dayLowLimitDown": false, "dayLowLimitUp": false, "limitDown": false, "limitUp": false, "name": "\u8302\u77fd", "previousClose": "55.5", "price": "53.2", "rank": "34", "symbol": "2342.TW", "turnoverK": "1888019", "volume": "34457000", "previousLimitUp": false, "previousLimitDown": false, "previousChange": null, "previousChangePercent": null, "holdK": null, "holdPercent": null, "overboughtK": null, "oversoldK": null, "boughtK": null, "soldK": null, "regularMarketDayHigh": "57.0", "regularMarketDayLow": "53.0", "rowId": "2342.TW", "symbolName": "\u8302\u77fd", "volK": 34457, "prevRank": "21", "inRankCount": 3}, {"change": "2.0", "changePercent": "+1.82%", "dayHigh": "113.0", "dayHighLimitDown": false, "dayHighLimitUp": false, "dayHighLowDiff": "3.00", "dayLow": "110.0", "dayLowLimitDown": false, "dayLowLimitUp": false, "limitDown": false, "limitUp": false, "name": "\u5f37\u8302", "previousClose": "110.0", "price": "112.0", "rank": "35", "symbol": "2481.TW", "turnoverK": "1875106", "volume": "16754000", "previousLimitUp": false, "previousLimitDown": false, "previousChange": null, "previousChangePercent": null, "holdK": null, "holdPercent": null, "overboughtK": null, "oversoldK": null, "boughtK": null, "soldK": null, "regularMarketDayHigh": "113.0", "regularMarketDayLow": "110.0", "rowId": "2481.TW", "symbolName": "\u5f37\u8302", "volK": 16754, "prevRank": "16", "inRankCount": 54}, {"change": "0.7", "changePercent": "+0.93%", "dayHigh": "76.0", "dayHighLimitDown": false, "dayHighLimitUp": false, "dayHighLowDiff": "1.00", "dayLow": "75.0", "dayLowLimitDown": false, "dayLowLimitUp": false, "limitDown": false, "limitUp": false, "name": "\u5bcc\u90a6\u91d1", "previousClose": "75.3", "price": "76.0", "rank": "36", "symbol": "2881.TW", "turnoverK": "1865661", "volume": "24710000", "previousLimitUp": false, "previousLimitDown": false, "previousChange": null, "previousChangePercent": null, "holdK": null, "holdPercent": null, "overboughtK": null, "oversoldK": null, "boughtK": null, "soldK": null, "regularMarketDayHigh": "76.0", "regularMarketDayLow": "75.0", "rowId": "2881.TW", "symbolName": "\u5bcc\u90a6\u91d1", "volK": 24710, "prevRank": "46", "inRankCount": 108}, {"change": "-8.0", "changePercent": "-3.52%", "dayHigh": "235.5", "dayHighLimitDown": false, "dayHighLimitUp": false, "dayHighLowDiff": "18.00", "dayLow": "217.5", "dayLowLimitDown": false, "dayLowLimitUp": false, "limitDown": false, "limitUp": false, "name": "\u60e0\u7279", "previousClose": "227.5", "price": "219.5", "rank": "37", "symbol": "6706.TW", "turnoverK": "1865105", "volume": "8307000", "previousLimitUp": false, "previousLimitDown": false, "previousChange": null, "previousChangePercent": null, "holdK": null, "holdPercent": null, "overboughtK": null, "oversoldK": null, "boughtK": null, "soldK": null, "regularMarketDayHigh": "235.5", "regularMarketDayLow": "217.5", "rowId": "6706.TW", "symbolName": "\u60e0\u7279", "volK": 8307, "prevRank": "47", "inRankCount": 4}, {"change": "1.3", "changePercent": "+2.19%", "dayHigh": "62.9", "dayHighLimitDown": false, "dayHighLimitUp": false, "dayHighLowDiff": "3.00", "dayLow": "59.9", "dayLowLimitDown": false, "dayLowLimitUp": false, "limitDown": false, "limitUp": false, "name": "\u88d5\u6c11", "previousClose": "59.3", "price": "60.6", "rank": "38", "symbol": "2606.TW", "turnoverK": "1814475", "volume": "29717000", "previousLimitUp": false, "previousLimitDown": false, "previousChange": null, "previousChangePercent": null, "holdK": null, "holdPercent": null, "overboughtK": null, "oversoldK": null, "boughtK": null, "soldK": null, "regularMarketDayHigh": "62.9", "regularMarketDayLow": "59.9", "rowId": "2606.TW", "symbolName": "\u88d5\u6c11", "volK": 29717, "prevRank": "71", "inRankCount": 5}, {"change": "-0.25", "changePercent": "-0.73%", "dayHigh": "34.85", "dayHighLimitDown": false, "dayHighLimitUp": false, "dayHighLowDiff": "0.75", "dayLow": "34.10", "dayLowLimitDown": false, "dayLowLimitUp": false, "limitDown": false, "limitUp": false, "name": "\u4e2d\u92fc", "previousClose": "34.35", "price": "34.10", "rank": "39", "symbol": "2002.TW", "turnoverK": "1801857", "volume": "52328000", "previousLimitUp": false, "previousLimitDown": false, "previousChange": null, "previousChangePercent": null, "holdK": null, "holdPercent": null, "overboughtK": null, "oversoldK": null, "boughtK": null, "soldK": null, "regularMarketDayHigh": "34.85", "regularMarketDayLow": "34.10", "rowId": "2002.TW", "symbolName": "\u4e2d\u92fc", "volK": 52328, "prevRank": "40", "inRankCount": 133}, {"change": "1.4", "changePercent": "+1.44%", "dayHigh": "100.5", "dayHighLimitDown": false, "dayHighLimitUp": false, "dayHighLowDiff": "2.90", "dayLow": "97.6", "dayLowLimitDown": false, "dayLowLimitUp": false, "limitDown": false, "limitUp": false, "name": "\u4e9e\u5149", "previousClose": "97.1", "price": "98.5", "rank": "40", "symbol": "3019.TW", "turnoverK": "1758683", "volume": "17722000", "previousLimitUp": false, "previousLimitDown": false, "previousChange": null, "previousChangePercent": null, "holdK": null, "holdPercent": null, "overboughtK": null, "oversoldK": null, "boughtK": null, "soldK": null, "regularMarketDayHigh": "100.5", "regularMarketDayLow": "97.6", "rowId": "3019.TW", "symbolName": "\u4e9e\u5149", "volK": 17722, "prevRank": "70", "inRankCount": 15}, {"change": "2.85", "changePercent": "+7.48%", "dayHigh": "41.90", "dayHighLimitDown": false, "dayHighLimitUp": true, "dayHighLowDiff": "3.15", "dayLow": "38.75", "dayLowLimitDown": false, "dayLowLimitUp": false, "limitDown": false, "limitUp": false, "name": "\u83ef\u6676\u79d1", "previousClose": "38.10", "price": "40.95", "rank": "41", "symbol": "3059.TW", "turnoverK": "1748765", "volume": "42383000", "previousLimitUp": false, "previousLimitDown": false, "previousChange": null, "previousChangePercent": null, "holdK": null, "holdPercent": null, "overboughtK": null, "oversoldK": null, "boughtK": null, "soldK": null, "regularMarketDayHigh": "41.90", "regularMarketDayLow": "38.75", "rowId": "3059.TW", "symbolName": "\u83ef\u6676\u79d1", "volK": 42383, "inRankCount": 1}, {"change": "-0.55", "changePercent": "-1.6%", "dayHigh": "34.80", "dayHighLimitDown": false, "dayHighLimitUp": false, "dayHighLowDiff": "0.90", "dayLow": "33.90", "dayLowLimitDown": false, "dayLowLimitUp": false, "limitDown": false, "limitUp": false, "name": "\u5927\u540c", "previousClose": "34.45", "price": "33.90", "rank": "42", "symbol": "2371.TW", "turnoverK": "1729911", "volume": "50695000", "previousLimitUp": false, "previousLimitDown": false, "previousChange": null, "previousChangePercent": null, "holdK": null, "holdPercent": null, "overboughtK": null, "oversoldK": null, "boughtK": null, "soldK": null, "regularMarketDayHigh": "34.80", "regularMarketDayLow": "33.90", "rowId": "2371.TW", "symbolName": "\u5927\u540c", "volK": 50695, "prevRank": "28", "inRankCount": 25}, {"change": "-2.0", "changePercent": "-1.2%", "dayHigh": "169.5", "dayHighLimitDown": false, "dayHighLimitUp": false, "dayHighLowDiff": "5.50", "dayLow": "164.0", "dayLowLimitDown": false, "dayLowLimitUp": false, "limitDown": false, "limitUp": false, "name": "\u6676\u8c6a\u79d1", "previousClose": "166.0", "price": "164.0", "rank": "43", "symbol": "3006.TW", "turnoverK": "1667728", "volume": "10012000", "previousLimitUp": false, "previousLimitDown": false, "previousChange": null, "previousChangePercent": null, "holdK": null, "holdPercent": null, "overboughtK": null, "oversoldK": null, "boughtK": null, "soldK": null, "regularMarketDayHigh": "169.5", "regularMarketDayLow": "164.0", "rowId": "3006.TW", "symbolName": "\u6676\u8c6a\u79d1", "volK": 10012, "prevRank": "24", "inRankCount": 133}, {"change": "-35", "changePercent": "-1.84%", "dayHigh": "1955", "dayHighLimitDown": false, "dayHighLimitUp": false, "dayHighLowDiff": "90.00", "dayLow": "1865", "dayLowLimitDown": false, "dayLowLimitUp": false, "limitDown": false, "limitUp": false, "name": "\u7965\u78a9", "previousClose": "1900", "price": "1865", "rank": "44", "symbol": "5269.TW", "turnoverK": "1637020", "volume": "861000", "previousLimitUp": false, "previousLimitDown": false, "previousChange": null, "previousChangePercent": null, "holdK": null, "holdPercent": null, "overboughtK": null, "oversoldK": null, "boughtK": null, "soldK": null, "regularMarketDayHigh": "1955", "regularMarketDayLow": "1865", "rowId": "5269.TW", "symbolName": "\u7965\u78a9", "volK": 861, "prevRank": "36", "inRankCount": 22}, {"change": "1", "changePercent": "+0.19%", "dayHigh": "528", "dayHighLimitDown": false, "dayHighLimitUp": false, "dayHighLowDiff": "16.00", "dayLow": "512", "dayLowLimitDown": false, "dayLowLimitUp": false, "limitDown": false, "limitUp": false, "name": "\u611b\u666e*", "previousClose": "513", "price": "514", "rank": "45", "symbol": "6531.TW", "turnoverK": "1565057", "volume": "3010000", "previousLimitUp": false, "previousLimitDown": false, "previousChange": null, "previousChangePercent": null, "holdK": null, "holdPercent": null, "overboughtK": null, "oversoldK": null, "boughtK": null, "soldK": null, "regularMarketDayHigh": "528", "regularMarketDayLow": "512", "rowId": "6531.TW", "symbolName": "\u611b\u666e*", "volK": 3010, "prevRank": "33", "inRankCount": 38}, {"change": "-1.0", "changePercent": "-0.68%", "dayHigh": "153.5", "dayHighLimitDown": false, "dayHighLimitUp": false, "dayHighLowDiff": "8.50", "dayLow": "145.0", "dayLowLimitDown": false, "dayLowLimitUp": false, "limitDown": false, "limitUp": false, "name": "\u53f0\u9a4a\u6295\u63a7", "previousClose": "148.0", "price": "147.0", "rank": "46", "symbol": "2636.TW", "turnoverK": "1561203", "volume": "10464000", "previousLimitUp": false, "previousLimitDown": false, "previousChange": null, "previousChangePercent": null, "holdK": null, "holdPercent": null, "overboughtK": null, "oversoldK": null, "boughtK": null, "soldK": null, "regularMarketDayHigh": "153.5", "regularMarketDayLow": "145.0", "rowId": "2636.TW", "symbolName": "\u53f0\u9a4a\u6295\u63a7", "volK": 10464, "prevRank": "54", "inRankCount": 7}, {"change": "0.55", "changePercent": "+0.39%", "dayHigh": "143.60", "dayHighLimitDown": false, "dayHighLimitUp": false, "dayHighLowDiff": "1.30", "dayLow": "142.30", "dayLowLimitDown": false, "dayLowLimitUp": false, "limitDown": false, "limitUp": false, "name": "\u5143\u5927\u53f0\u706350", "previousClose": "141.80", "price": "142.35", "rank": "47", "symbol": "0050.TW", "turnoverK": "1550557", "volume": "10858000", "previousLimitUp": false, "previousLimitDown": false, "previousChange": null, "previousChangePercent": null, "holdK": null, "holdPercent": null, "overboughtK": null, "oversoldK": null, "boughtK": null, "soldK": null, "regularMarketDayHigh": "143.60", "regularMarketDayLow": "142.30", "rowId": "0050.TW", "symbolName": "\u5143\u5927\u53f0\u706350", "volK": 10858, "inRankCount": 1}, {"change": "-0.05", "changePercent": "-0.19%", "dayHigh": "26.00", "dayHighLimitDown": false, "dayHighLimitUp": false, "dayHighLowDiff": "0.30", "dayLow": "25.70", "dayLowLimitDown": false, "dayLowLimitUp": false, "limitDown": false, "limitUp": false, "name": "\u4e2d\u4fe1\u91d1", "previousClose": "26.00", "price": "25.95", "rank": "48", "symbol": "2891.TW", "turnoverK": "1474721", "volume": "56991000", "previousLimitUp": false, "previousLimitDown": false, "previousChange": null, "previousChangePercent": null, "holdK": null, "holdPercent": null, "overboughtK": null, "oversoldK": null, "boughtK": null, "soldK": null, "regularMarketDayHigh": "26.00", "regularMarketDayLow": "25.70", "rowId": "2891.TW", "symbolName": "\u4e2d\u4fe1\u91d1", "volK": 56991, "prevRank": "51", "inRankCount": 16}, {"change": "-6.5", "changePercent": "-1.77%", "dayHigh": "368.0", "dayHighLimitDown": false, "dayHighLimitUp": false, "dayHighLowDiff": "8.00", "dayLow": "360.0", "dayLowLimitDown": false, "dayLowLimitUp": false, "limitDown": false, "limitUp": false, "name": "\u83ef\u78a9", "previousClose": "366.5", "price": "360.0", "rank": "49", "symbol": "2357.TW", "turnoverK": "1435172", "volume": "3960000", "previousLimitUp": false, "previousLimitDown": false, "previousChange": null, "previousChangePercent": null, "holdK": null, "holdPercent": null, "overboughtK": null, "oversoldK": null, "boughtK": null, "soldK": null, "regularMarketDayHigh": "368.0", "regularMarketDayLow": "360.0", "rowId": "2357.TW", "symbolName": "\u83ef\u78a9", "volK": 3960, "inRankCount": 1}, {"change": "5.0", "changePercent": "+1.63%", "dayHigh": "313.0", "dayHighLimitDown": false, "dayHighLimitUp": false, "dayHighLowDiff": "5.50", "dayLow": "307.5", "dayLowLimitDown": false, "dayLowLimitUp": false, "limitDown": false, "limitUp": false, "name": "\u77fd\u5275", "previousClose": "306.0", "price": "311.0", "rank": "50", "symbol": "8016.TW", "turnoverK": "1429592", "volume": "4612000", "previousLimitUp": false, "previousLimitDown": false, "previousChange": null, "previousChangePercent": null, "holdK": null, "holdPercent": null, "overboughtK": null, "oversoldK": null, "boughtK": null, "soldK": null, "regularMarketDayHigh": "313.0", "regularMarketDayLow": "307.5", "rowId": "8016.TW", "symbolName": "\u77fd\u5275", "volK": 4612, "prevRank": "55", "inRankCount": 6}, {"change": "0.4", "changePercent": "+0.53%", "dayHigh": "78.8", "dayHighLimitDown": false, "dayHighLimitUp": false, "dayHighLowDiff": "3.90", "dayLow": "74.9", "dayLowLimitDown": false, "dayLowLimitUp": false, "limitDown": false, "limitUp": false, "name": "\u6167\u6d0b-KY", "previousClose": "75.3", "price": "75.7", "rank": "51", "symbol": "2637.TW", "turnoverK": "1424437", "volume": "18603000", "previousLimitUp": false, "previousLimitDown": false, "previousChange": null, "previousChangePercent": null, "holdK": null, "holdPercent": null, "overboughtK": null, "oversoldK": null, "boughtK": null, "soldK": null, "regularMarketDayHigh": "78.8", "regularMarketDayLow": "74.9", "rowId": "2637.TW", "symbolName": "\u6167\u6d0b-KY", "volK": 18603, "inRankCount": 1}, {"change": "12.5", "changePercent": "+9.77%", "dayHigh": "140.5", "dayHighLimitDown": false, "dayHighLimitUp": true, "dayHighLowDiff": "7.50", "dayLow": "133.0", "dayLowLimitDown": false, "dayLowLimitUp": false, "limitDown": false, "limitUp": true, "name": "\u805a\u9f0e", "previousClose": "128.0", "price": "140.5", "rank": "52", "symbol": "6224.TW", "turnoverK": "1413816", "volume": "10199000", "previousLimitUp": false, "previousLimitDown": false, "previousChange": null, "previousChangePercent": null, "holdK": null, "holdPercent": null, "overboughtK": null, "oversoldK": null, "boughtK": null, "soldK": null, "regularMarketDayHigh": "140.5", "regularMarketDayLow": "133.0", "rowId": "6224.TW", "symbolName": "\u805a\u9f0e", "volK": 10199, "inRankCount": 1}, {"change": "0.5", "changePercent": "+0.87%", "dayHigh": "58.6", "dayHighLimitDown": false, "dayHighLimitUp": false, "dayHighLowDiff": "1.40", "dayLow": "57.2", "dayLowLimitDown": false, "dayLowLimitUp": false, "limitDown": false, "limitUp": false, "name": "\u5149\u78ca", "previousClose": "57.3", "price": "57.8", "rank": "53", "symbol": "2340.TW", "turnoverK": "1382312", "volume": "23872000", "previousLimitUp": false, "previousLimitDown": false, "previousChange": null, "previousChangePercent": null, "holdK": null, "holdPercent": null, "overboughtK": null, "oversoldK": null, "boughtK": null, "soldK": null, "regularMarketDayHigh": "58.6", "regularMarketDayLow": "57.2", "rowId": "2340.TW", "symbolName": "\u5149\u78ca", "volK": 23872, "prevRank": "31", "inRankCount": 35}, {"change": "0.0", "changePercent": "0%", "dayHigh": "178.0", "dayHighLimitDown": false, "dayHighLimitUp": false, "dayHighLowDiff": "5.50", "dayLow": "172.5", "dayLowLimitDown": false, "dayLowLimitUp": false, "limitDown": false, "limitUp": false, "name": "\u6566\u6cf0", "previousClose": "173.0", "price": "173.0", "rank": "54", "symbol": "3545.TW", "turnoverK": "1309298", "volume": "7497000", "previousLimitUp": false, "previousLimitDown": false, "previousChange": null, "previousChangePercent": null, "holdK": null, "holdPercent": null, "overboughtK": null, "oversoldK": null, "boughtK": null, "soldK": null, "regularMarketDayHigh": "178.0", "regularMarketDayLow": "172.5", "rowId": "3545.TW", "symbolName": "\u6566\u6cf0", "volK": 7497, "prevRank": "27", "inRankCount": 133}, {"change": "2.85", "changePercent": "+7.35%", "dayHigh": "42.05", "dayHighLimitDown": false, "dayHighLimitUp": false, "dayHighLowDiff": "3.35", "dayLow": "38.70", "dayLowLimitDown": false, "dayLowLimitUp": false, "limitDown": false, "limitUp": false, "name": "\u7cbe\u6210\u79d1", "previousClose": "38.75", "price": "41.60", "rank": "55", "symbol": "6191.TW", "turnoverK": "1302318", "volume": "32098000", "previousLimitUp": false, "previousLimitDown": false, "previousChange": null, "previousChangePercent": null, "holdK": null, "holdPercent": null, "overboughtK": null, "oversoldK": null, "boughtK": null, "soldK": null, "regularMarketDayHigh": "42.05", "regularMarketDayLow": "38.70", "rowId": "6191.TW", "symbolName": "\u7cbe\u6210\u79d1", "volK": 32098, "inRankCount": 1}, {"change": "1.00", "changePercent": "+2.29%", "dayHigh": "48.10", "dayHighLimitDown": false, "dayHighLimitUp": true, "dayHighLowDiff": "4.10", "dayLow": "44.00", "dayLowLimitDown": false, "dayLowLimitUp": false, "limitDown": false, "limitUp": false, "name": "\u5a01\u81f4", "previousClose": "43.75", "price": "44.75", "rank": "56", "symbol": "2028.TW", "turnoverK": "1263146", "volume": "26942000", "previousLimitUp": false, "previousLimitDown": false, "previousChange": null, "previousChangePercent": null, "holdK": null, "holdPercent": null, "overboughtK": null, "oversoldK": null, "boughtK": null, "soldK": null, "regularMarketDayHigh": "48.10", "regularMarketDayLow": "44.00", "rowId": "2028.TW", "symbolName": "\u5a01\u81f4", "volK": 26942, "inRankCount": 1}, {"change": "0.75", "changePercent": "+2.68%", "dayHigh": "30.15", "dayHighLimitDown": false, "dayHighLimitUp": false, "dayHighLowDiff": "2.05", "dayLow": "28.10", "dayLowLimitDown": false, "dayLowLimitUp": false, "limitDown": false, "limitUp": false, "name": "\u4e09\u6643", "previousClose": "27.95", "price": "28.70", "rank": "57", "symbol": "1721.TW", "turnoverK": "1243455", "volume": "42542000", "previousLimitUp": false, "previousLimitDown": false, "previousChange": null, "previousChangePercent": null, "holdK": null, "holdPercent": null, "overboughtK": null, "oversoldK": null, "boughtK": null, "soldK": null, "regularMarketDayHigh": "30.15", "regularMarketDayLow": "28.10", "rowId": "1721.TW", "symbolName": "\u4e09\u6643", "volK": 42542, "prevRank": "86", "inRankCount": 7}, {"change": "0.5", "changePercent": "+0.3%", "dayHigh": "169.0", "dayHighLimitDown": false, "dayHighLimitUp": false, "dayHighLowDiff": "4.00", "dayLow": "165.0", "dayLowLimitDown": false, "dayLowLimitUp": false, "limitDown": false, "limitUp": false, "name": "\u5fae\u661f", "previousClose": "165.5", "price": "166.0", "rank": "58", "symbol": "2377.TW", "turnoverK": "1231769", "volume": "7373000", "previousLimitUp": false, "previousLimitDown": false, "previousChange": null, "previousChangePercent": null, "holdK": null, "holdPercent": null, "overboughtK": null, "oversoldK": null, "boughtK": null, "soldK": null, "regularMarketDayHigh": "169.0", "regularMarketDayLow": "165.0", "rowId": "2377.TW", "symbolName": "\u5fae\u661f", "volK": 7373, "prevRank": "67", "inRankCount": 8}, {"change": "0", "changePercent": "0%", "dayHigh": "579", "dayHighLimitDown": false, "dayHighLimitUp": false, "dayHighLowDiff": "14.00", "dayLow": "565", "dayLowLimitDown": false, "dayLowLimitUp": false, "limitDown": false, "limitUp": false, "name": "\u745e\u6631", "previousClose": "565", "price": "565", "rank": "59", "symbol": "2379.TW", "turnoverK": "1198087", "volume": "2101000", "previousLimitUp": false, "previousLimitDown": false, "previousChange": null, "previousChangePercent": null, "holdK": null, "holdPercent": null, "overboughtK": null, "oversoldK": null, "boughtK": null, "soldK": null, "regularMarketDayHigh": "579", "regularMarketDayLow": "565", "rowId": "2379.TW", "symbolName": "\u745e\u6631", "volK": 2101, "prevRank": "42", "inRankCount": 9}, {"change": "40", "changePercent": "+3.96%", "dayHigh": "1075", "dayHighLimitDown": false, "dayHighLimitUp": false, "dayHighLowDiff": "45.00", "dayLow": "1030", "dayLowLimitDown": false, "dayLowLimitUp": false, "limitDown": false, "limitUp": false, "name": "\u7def\u7a4e", "previousClose": "1010", "price": "1050", "rank": "60", "symbol": "6669.TW", "turnoverK": "1196850", "volume": "1139000", "previousLimitUp": false, "previousLimitDown": false, "previousChange": null, "previousChangePercent": null, "holdK": null, "holdPercent": null, "overboughtK": null, "oversoldK": null, "boughtK": null, "soldK": null, "regularMarketDayHigh": "1075", "regularMarketDayLow": "1030", "rowId": "6669.TW", "symbolName": "\u7def\u7a4e", "volK": 1139, "prevRank": "83", "inRankCount": 8}, {"change": "-0.6", "changePercent": "-0.77%", "dayHigh": "78.8", "dayHighLimitDown": false, "dayHighLimitUp": false, "dayHighLowDiff": "1.90", "dayLow": "76.9", "dayLowLimitDown": false, "dayLowLimitUp": false, "limitDown": false, "limitUp": false, "name": "\u5357\u4e9e\u79d1", "previousClose": "77.5", "price": "76.9", "rank": "61", "symbol": "2408.TW", "turnoverK": "1190323", "volume": "15336000", "previousLimitUp": false, "previousLimitDown": false, "previousChange": null, "previousChangePercent": null, "holdK": null, "holdPercent": null, "overboughtK": null, "oversoldK": null, "boughtK": null, "soldK": null, "regularMarketDayHigh": "78.8", "regularMarketDayLow": "76.9", "rowId": "2408.TW", "symbolName": "\u5357\u4e9e\u79d1", "volK": 15336, "prevRank": "89", "inRankCount": 14}, {"change": "0.0", "changePercent": "0%", "dayHigh": "61.2", "dayHighLimitDown": false, "dayHighLimitUp": false, "dayHighLowDiff": "0.60", "dayLow": "60.6", "dayLowLimitDown": false, "dayLowLimitUp": false, "limitDown": false, "limitUp": false, "name": "\u570b\u6cf0\u91d1", "previousClose": "60.7", "price": "60.7", "rank": "62", "symbol": "2882.TW", "turnoverK": "1184347", "volume": "19461000", "previousLimitUp": false, "previousLimitDown": false, "previousChange": null, "previousChangePercent": null, "holdK": null, "holdPercent": null, "overboughtK": null, "oversoldK": null, "boughtK": null, "soldK": null, "regularMarketDayHigh": "61.2", "regularMarketDayLow": "60.6", "rowId": "2882.TW", "symbolName": "\u570b\u6cf0\u91d1", "volK": 19461, "prevRank": "62", "inRankCount": 20}, {"change": "1.15", "changePercent": "+4.3%", "dayHigh": "29.40", "dayHighLimitDown": false, "dayHighLimitUp": true, "dayHighLowDiff": "2.30", "dayLow": "27.10", "dayLowLimitDown": false, "dayLowLimitUp": false, "limitDown": false, "limitUp": false, "name": "\u8b41\u88d5", "previousClose": "26.75", "price": "27.90", "rank": "63", "symbol": "3419.TW", "turnoverK": "1182507", "volume": "41559000", "previousLimitUp": false, "previousLimitDown": false, "previousChange": null, "previousChangePercent": null, "holdK": null, "holdPercent": null, "overboughtK": null, "oversoldK": null, "boughtK": null, "soldK": null, "regularMarketDayHigh": "29.40", "regularMarketDayLow": "27.10", "rowId": "3419.TW", "symbolName": "\u8b41\u88d5", "volK": 41559, "prevRank": "88", "inRankCount": 2}, {"change": "0.41", "changePercent": "+1.84%", "dayHigh": "22.86", "dayHighLimitDown": false, "dayHighLimitUp": false, "dayHighLowDiff": "0.78", "dayLow": "22.08", "dayLowLimitDown": false, "dayLowLimitUp": false, "limitDown": false, "limitUp": false, "name": "\u5143\u5927\u6eec\u6df1300\u6b632", "previousClose": "22.33", "price": "22.74", "rank": "64", "symbol": "00637L.TW", "turnoverK": "1160593", "volume": "51500000", "previousLimitUp": false, "previousLimitDown": false, "previousChange": null, "previousChangePercent": null, "holdK": null, "holdPercent": null, "overboughtK": null, "oversoldK": null, "boughtK": null, "soldK": null, "regularMarketDayHigh": "22.86", "regularMarketDayLow": "22.08", "rowId": "00637L.TW", "symbolName": "\u5143\u5927\u6eec\u6df1300\u6b632", "volK": 51500, "prevRank": "76", "inRankCount": 3}, {"change": "9.5", "changePercent": "+4.09%", "dayHigh": "251.0", "dayHighLimitDown": false, "dayHighLimitUp": false, "dayHighLowDiff": "14.00", "dayLow": "237.0", "dayLowLimitDown": false, "dayLowLimitUp": false, "limitDown": false, "limitUp": false, "name": "\u4eac\u9f0e", "previousClose": "232.5", "price": "242.0", "rank": "65", "symbol": "3413.TW", "turnoverK": "1127681", "volume": "4643000", "previousLimitUp": false, "previousLimitDown": false, "previousChange": null, "previousChangePercent": null, "holdK": null, "holdPercent": null, "overboughtK": null, "oversoldK": null, "boughtK": null, "soldK": null, "regularMarketDayHigh": "251.0", "regularMarketDayLow": "237.0", "rowId": "3413.TW", "symbolName": "\u4eac\u9f0e", "volK": 4643, "inRankCount": 1}, {"change": "-14", "changePercent": "-1.39%", "dayHigh": "1045", "dayHighLimitDown": false, "dayHighLimitUp": false, "dayHighLowDiff": "54.00", "dayLow": "991", "dayLowLimitDown": false, "dayLowLimitUp": false, "limitDown": false, "limitUp": false, "name": "\u4e16\u82af-KY", "previousClose": "1005", "price": "991", "rank": "66", "symbol": "3661.TW", "turnoverK": "1104330", "volume": "1091000", "previousLimitUp": false, "previousLimitDown": false, "previousChange": null, "previousChangePercent": null, "holdK": null, "holdPercent": null, "overboughtK": null, "oversoldK": null, "boughtK": null, "soldK": null, "regularMarketDayHigh": "1045", "regularMarketDayLow": "991", "rowId": "3661.TW", "symbolName": "\u4e16\u82af-KY", "volK": 1091, "prevRank": "45", "inRankCount": 9}, {"change": "29", "changePercent": "+3.31%", "dayHigh": "905", "dayHighLimitDown": false, "dayHighLimitUp": false, "dayHighLowDiff": "24.00", "dayLow": "881", "dayLowLimitDown": false, "dayLowLimitUp": false, "limitDown": false, "limitUp": false, "name": "\u4e9e\u5fb7\u5ba2-KY", "previousClose": "876", "price": "905", "rank": "67", "symbol": "1590.TW", "turnoverK": "1104103", "volume": "1235000", "previousLimitUp": false, "previousLimitDown": false, "previousChange": null, "previousChangePercent": null, "holdK": null, "holdPercent": null, "overboughtK": null, "oversoldK": null, "boughtK": null, "soldK": null, "regularMarketDayHigh": "905", "regularMarketDayLow": "881", "rowId": "1590.TW", "symbolName": "\u4e9e\u5fb7\u5ba2-KY", "volK": 1235, "prevRank": "81", "inRankCount": 2}, {"change": "-2.0", "changePercent": "-0.76%", "dayHigh": "266.0", "dayHighLimitDown": false, "dayHighLimitUp": false, "dayHighLowDiff": "5.00", "dayLow": "261.0", "dayLowLimitDown": false, "dayLowLimitUp": false, "limitDown": false, "limitUp": false, "name": "\u53f0\u9054\u96fb", "previousClose": "263.0", "price": "261.0", "rank": "68", "symbol": "2308.TW", "turnoverK": "1086363", "volume": "4129000", "previousLimitUp": false, "previousLimitDown": false, "previousChange": null, "previousChangePercent": null, "holdK": null, "holdPercent": null, "overboughtK": null, "oversoldK": null, "boughtK": null, "soldK": null, "regularMarketDayHigh": "266.0", "regularMarketDayLow": "261.0", "rowId": "2308.TW", "symbolName": "\u53f0\u9054\u96fb", "volK": 4129, "prevRank": "72", "inRankCount": 103}, {"change": "-1.5", "changePercent": "-0.33%", "dayHigh": "461.0", "dayHighLimitDown": false, "dayHighLimitUp": false, "dayHighLowDiff": "6.50", "dayLow": "454.5", "dayLowLimitDown": false, "dayLowLimitUp": false, "limitDown": false, "limitUp": false, "name": "\u570b\u5de8", "previousClose": "456.0", "price": "454.5", "rank": "69", "symbol": "2327.TW", "turnoverK": "1082134", "volume": "2368000", "previousLimitUp": false, "previousLimitDown": false, "previousChange": null, "previousChangePercent": null, "holdK": null, "holdPercent": null, "overboughtK": null, "oversoldK": null, "boughtK": null, "soldK": null, "regularMarketDayHigh": "461.0", "regularMarketDayLow": "454.5", "rowId": "2327.TW", "symbolName": "\u570b\u5de8", "volK": 2368, "prevRank": "38", "inRankCount": 19}, {"change": "-0.20", "changePercent": "-1.2%", "dayHigh": "16.80", "dayHighLimitDown": false, "dayHighLimitUp": false, "dayHighLowDiff": "0.30", "dayLow": "16.50", "dayLowLimitDown": false, "dayLowLimitUp": false, "limitDown": false, "limitUp": false, "name": "\u958b\u767c\u91d1", "previousClose": "16.70", "price": "16.50", "rank": "70", "symbol": "2883.TW", "turnoverK": "1080897", "volume": "65099000", "previousLimitUp": false, "previousLimitDown": false, "previousChange": null, "previousChangePercent": null, "holdK": null, "holdPercent": null, "overboughtK": null, "oversoldK": null, "boughtK": null, "soldK": null, "regularMarketDayHigh": "16.80", "regularMarketDayLow": "16.50", "rowId": "2883.TW", "symbolName": "\u958b\u767c\u91d1", "volK": 65099, "prevRank": "64", "inRankCount": 20}, {"change": "-0.40", "changePercent": "-1.32%", "dayHigh": "30.90", "dayHighLimitDown": false, "dayHighLimitUp": false, "dayHighLowDiff": "1.10", "dayLow": "29.80", "dayLowLimitDown": false, "dayLowLimitUp": false, "limitDown": false, "limitUp": false, "name": "\u5b8f\u7881", "previousClose": "30.30", "price": "29.90", "rank": "71", "symbol": "2353.TW", "turnoverK": "1062514", "volume": "35189000", "previousLimitUp": false, "previousLimitDown": false, "previousChange": null, "previousChangePercent": null, "holdK": null, "holdPercent": null, "overboughtK": null, "oversoldK": null, "boughtK": null, "soldK": null, "regularMarketDayHigh": "30.90", "regularMarketDayLow": "29.80", "rowId": "2353.TW", "symbolName": "\u5b8f\u7881", "volK": 35189, "prevRank": "53", "inRankCount": 8}, {"change": "8.3", "changePercent": "+9.92%", "dayHigh": "92.0", "dayHighLimitDown": false, "dayHighLimitUp": true, "dayHighLowDiff": "8.20", "dayLow": "83.8", "dayLowLimitDown": false, "dayLowLimitUp": false, "limitDown": false, "limitUp": true, "name": "\u5927\u773e\u63a7", "previousClose": "83.7", "price": "92.0", "rank": "72", "symbol": "3701.TW", "turnoverK": "1056444", "volume": "11865000", "previousLimitUp": false, "previousLimitDown": false, "previousChange": null, "previousChangePercent": null, "holdK": null, "holdPercent": null, "overboughtK": null, "oversoldK": null, "boughtK": null, "soldK": null, "regularMarketDayHigh": "92.0", "regularMarketDayLow": "83.8", "rowId": "3701.TW", "symbolName": "\u5927\u773e\u63a7", "volK": 11865, "prevRank": "95", "inRankCount": 6}, {"change": "-0.3", "changePercent": "-0.32%", "dayHigh": "97.4", "dayHighLimitDown": false, "dayHighLimitUp": false, "dayHighLowDiff": "3.20", "dayLow": "94.2", "dayLowLimitDown": false, "dayLowLimitUp": false, "limitDown": false, "limitUp": false, "name": "\u5049\u8a6e\u96fb", "previousClose": "95.0", "price": "94.7", "rank": "73", "symbol": "2436.TW", "turnoverK": "1043977", "volume": "10892000", "previousLimitUp": false, "previousLimitDown": false, "previousChange": null, "previousChangePercent": null, "holdK": null, "holdPercent": null, "overboughtK": null, "oversoldK": null, "boughtK": null, "soldK": null, "regularMarketDayHigh": "97.4", "regularMarketDayLow": "94.2", "rowId": "2436.TW", "symbolName": "\u5049\u8a6e\u96fb", "volK": 10892, "prevRank": "43", "inRankCount": 23}, {"change": "-0.05", "changePercent": "-0.16%", "dayHigh": "32.15", "dayHighLimitDown": false, "dayHighLimitUp": false, "dayHighLowDiff": "0.75", "dayLow": "31.40", "dayLowLimitDown": false, "dayLowLimitUp": false, "limitDown": false, "limitUp": false, "name": "\u83ef\u90a6\u96fb", "previousClose": "31.50", "price": "31.45", "rank": "74", "symbol": "2344.TW", "turnoverK": "1043618", "volume": "32831000", "previousLimitUp": false, "previousLimitDown": false, "previousChange": null, "previousChangePercent": null, "holdK": null, "holdPercent": null, "overboughtK": null, "oversoldK": null, "boughtK": null, "soldK": null, "regularMarketDayHigh": "32.15", "regularMarketDayLow": "31.40", "rowId": "2344.TW", "symbolName": "\u83ef\u90a6\u96fb", "volK": 32831, "prevRank": "49", "inRankCount": 27}, {"change": "3.0", "changePercent": "+1.96%", "dayHigh": "161.5", "dayHighLimitDown": false, "dayHighLimitUp": false, "dayHighLowDiff": "6.00", "dayLow": "155.5", "dayLowLimitDown": false, "dayLowLimitUp": false, "limitDown": false, "limitUp": false, "name": "\u5e06\u5ba3", "previousClose": "153.0", "price": "156.0", "rank": "75", "symbol": "6196.TW", "turnoverK": "1043148", "volume": "6602000", "previousLimitUp": false, "previousLimitDown": false, "previousChange": null, "previousChangePercent": null, "holdK": null, "holdPercent": null, "overboughtK": null, "oversoldK": null, "boughtK": null, "soldK": null, "regularMarketDayHigh": "161.5", "regularMarketDayLow": "155.5", "rowId": "6196.TW", "symbolName": "\u5e06\u5ba3", "volK": 6602, "inRankCount": 1}, {"change": "0.10", "changePercent": "+0.4%", "dayHigh": "25.10", "dayHighLimitDown": false, "dayHighLimitUp": false, "dayHighLowDiff": "0.20", "dayLow": "24.90", "dayLowLimitDown": false, "dayLowLimitUp": false, "limitDown": false, "limitUp": false, "name": "\u5143\u5927\u91d1", "previousClose": "24.95", "price": "25.05", "rank": "76", "symbol": "2885.TW", "turnoverK": "1028631", "volume": "41114000", "previousLimitUp": false, "previousLimitDown": false, "previousChange": null, "previousChangePercent": null, "holdK": null, "holdPercent": null, "overboughtK": null, "oversoldK": null, "boughtK": null, "soldK": null, "regularMarketDayHigh": "25.10", "regularMarketDayLow": "24.90", "rowId": "2885.TW", "symbolName": "\u5143\u5927\u91d1", "volK": 41114, "inRankCount": 1}, {"change": "0.30", "changePercent": "+1.02%", "dayHigh": "30.25", "dayHighLimitDown": false, "dayHighLimitUp": false, "dayHighLowDiff": "1.70", "dayLow": "28.55", "dayLowLimitDown": false, "dayLowLimitUp": false, "limitDown": false, "limitUp": false, "name": "\u83ef\u5b5a", "previousClose": "29.40", "price": "29.70", "rank": "77", "symbol": "6235.TW", "turnoverK": "1012308", "volume": "34350000", "previousLimitUp": false, "previousLimitDown": false, "previousChange": null, "previousChangePercent": null, "holdK": null, "holdPercent": null, "overboughtK": null, "oversoldK": null, "boughtK": null, "soldK": null, "regularMarketDayHigh": "30.25", "regularMarketDayLow": "28.55", "rowId": "6235.TW", "symbolName": "\u83ef\u5b5a", "volK": 34350, "prevRank": "34", "inRankCount": 2}, {"change": "5.9", "changePercent": "+9.92%", "dayHigh": "65.4", "dayHighLimitDown": false, "dayHighLimitUp": true, "dayHighLowDiff": "3.80", "dayLow": "61.6", "dayLowLimitDown": false, "dayLowLimitUp": false, "limitDown": false, "limitUp": true, "name": "\u9338\u5bf6", "previousClose": "59.5", "price": "65.4", "rank": "78", "symbol": "8104.TW", "turnoverK": "996896", "volume": "15513000", "previousLimitUp": false, "previousLimitDown": false, "previousChange": null, "previousChangePercent": null, "holdK": null, "holdPercent": null, "overboughtK": null, "oversoldK": null, "boughtK": null, "soldK": null, "regularMarketDayHigh": "65.4", "regularMarketDayLow": "61.6", "rowId": "8104.TW", "symbolName": "\u9338\u5bf6", "volK": 15513, "inRankCount": 1}, {"change": "-5", "changePercent": "-0.24%", "dayHigh": "2090", "dayHighLimitDown": false, "dayHighLimitUp": false, "dayHighLowDiff": "30.00", "dayLow": "2060", "dayLowLimitDown": false, "dayLowLimitUp": false, "limitDown": false, "limitUp": false, "name": "\u5927\u7acb\u5149", "previousClose": "2065", "price": "2060", "rank": "79", "symbol": "3008.TW", "turnoverK": "965355", "volume": "465000", "previousLimitUp": false, "previousLimitDown": false, "previousChange": null, "previousChangePercent": null, "holdK": null, "holdPercent": null, "overboughtK": null, "oversoldK": null, "boughtK": null, "soldK": null, "regularMarketDayHigh": "2090", "regularMarketDayLow": "2060", "rowId": "3008.TW", "symbolName": "\u5927\u7acb\u5149", "volK": 465, "prevRank": "60", "inRankCount": 8}, {"change": "0.25", "changePercent": "+0.81%", "dayHigh": "33.15", "dayHighLimitDown": false, "dayHighLimitUp": false, "dayHighLowDiff": "2.35", "dayLow": "30.80", "dayLowLimitDown": false, "dayLowLimitUp": false, "limitDown": false, "limitUp": false, "name": "\u65b0\u8208", "previousClose": "30.95", "price": "31.20", "rank": "80", "symbol": "2605.TW", "turnoverK": "948739", "volume": "29892000", "previousLimitUp": false, "previousLimitDown": false, "previousChange": null, "previousChangePercent": null, "holdK": null, "holdPercent": null, "overboughtK": null, "oversoldK": null, "boughtK": null, "soldK": null, "regularMarketDayHigh": "33.15", "regularMarketDayLow": "30.80", "rowId": "2605.TW", "symbolName": "\u65b0\u8208", "volK": 29892, "inRankCount": 1}, {"change": "1.0", "changePercent": "+0.97%", "dayHigh": "106.0", "dayHighLimitDown": false, "dayHighLimitUp": false, "dayHighLowDiff": "2.00", "dayLow": "104.0", "dayLowLimitDown": false, "dayLowLimitUp": false, "limitDown": false, "limitUp": false, "name": "\u53f0\u5851", "previousClose": "103.5", "price": "104.5", "rank": "81", "symbol": "1301.TW", "turnoverK": "895484", "volume": "8546000", "previousLimitUp": false, "previousLimitDown": false, "previousChange": null, "previousChangePercent": null, "holdK": null, "holdPercent": null, "overboughtK": null, "oversoldK": null, "boughtK": null, "soldK": null, "regularMarketDayHigh": "106.0", "regularMarketDayLow": "104.0", "rowId": "1301.TW", "symbolName": "\u53f0\u5851", "volK": 8546, "prevRank": "90", "inRankCount": 3}, {"change": "0.9", "changePercent": "+1.1%", "dayHigh": "85.6", "dayHighLimitDown": false, "dayHighLimitUp": false, "dayHighLowDiff": "3.60", "dayLow": "82.0", "dayLowLimitDown": false, "dayLowLimitUp": false, "limitDown": false, "limitUp": false, "name": "\u6607\u8cbf", "previousClose": "81.8", "price": "82.7", "rank": "82", "symbol": "3305.TW", "turnoverK": "878258", "volume": "10446000", "previousLimitUp": false, "previousLimitDown": false, "previousChange": null, "previousChangePercent": null, "holdK": null, "holdPercent": null, "overboughtK": null, "oversoldK": null, "boughtK": null, "soldK": null, "regularMarketDayHigh": "85.6", "regularMarketDayLow": "82.0", "rowId": "3305.TW", "symbolName": "\u6607\u8cbf", "volK": 10446, "prevRank": "61", "inRankCount": 2}, {"change": "4.0", "changePercent": "+1.38%", "dayHigh": "297.0", "dayHighLimitDown": false, "dayHighLimitUp": false, "dayHighLowDiff": "6.00", "dayLow": "291.0", "dayLowLimitDown": false, "dayLowLimitUp": false, "limitDown": false, "limitUp": false, "name": "\u540c\u6b23\u96fb", "previousClose": "289.0", "price": "293.0", "rank": "83", "symbol": "6271.TW", "turnoverK": "857164", "volume": "2916000", "previousLimitUp": false, "previousLimitDown": false, "previousChange": null, "previousChangePercent": null, "holdK": null, "holdPercent": null, "overboughtK": null, "oversoldK": null, "boughtK": null, "soldK": null, "regularMarketDayHigh": "297.0", "regularMarketDayLow": "291.0", "rowId": "6271.TW", "symbolName": "\u540c\u6b23\u96fb", "volK": 2916, "prevRank": "98", "inRankCount": 111}, {"change": "0.15", "changePercent": "+0.48%", "dayHigh": "33.05", "dayHighLimitDown": false, "dayHighLimitUp": false, "dayHighLowDiff": "1.55", "dayLow": "31.50", "dayLowLimitDown": false, "dayLowLimitUp": false, "limitDown": false, "limitUp": false, "name": "\u5efa\u6f22", "previousClose": "31.45", "price": "31.60", "rank": "84", "symbol": "3062.TW", "turnoverK": "827025", "volume": "25692000", "previousLimitUp": false, "previousLimitDown": false, "previousChange": null, "previousChangePercent": null, "holdK": null, "holdPercent": null, "overboughtK": null, "oversoldK": null, "boughtK": null, "soldK": null, "regularMarketDayHigh": "33.05", "regularMarketDayLow": "31.50", "rowId": "3062.TW", "symbolName": "\u5efa\u6f22", "volK": 25692, "inRankCount": 1}, {"change": "0.00", "changePercent": "0%", "dayHigh": "10.90", "dayHighLimitDown": false, "dayHighLimitUp": false, "dayHighLowDiff": "0.15", "dayLow": "10.75", "dayLowLimitDown": false, "dayLowLimitUp": false, "limitDown": false, "limitUp": false, "name": "\u65b0\u5149\u91d1", "previousClose": "10.80", "price": "10.80", "rank": "85", "symbol": "2888.TW", "turnoverK": "821070", "volume": "75961000", "previousLimitUp": false, "previousLimitDown": false, "previousChange": null, "previousChangePercent": null, "holdK": null, "holdPercent": null, "overboughtK": null, "oversoldK": null, "boughtK": null, "soldK": null, "regularMarketDayHigh": "10.90", "regularMarketDayLow": "10.75", "rowId": "2888.TW", "symbolName": "\u65b0\u5149\u91d1", "volK": 75961, "prevRank": "78", "inRankCount": 16}, {"change": "-0.35", "changePercent": "-0.83%", "dayHigh": "42.65", "dayHighLimitDown": false, "dayHighLimitUp": false, "dayHighLowDiff": "0.75", "dayLow": "41.90", "dayLowLimitDown": false, "dayLowLimitUp": false, "limitDown": false, "limitUp": false, "name": "\u65fa\u5b8f", "previousClose": "42.30", "price": "41.95", "rank": "86", "symbol": "2337.TW", "turnoverK": "812003", "volume": "19288000", "previousLimitUp": false, "previousLimitDown": false, "previousChange": null, "previousChangePercent": null, "holdK": null, "holdPercent": null, "overboughtK": null, "oversoldK": null, "boughtK": null, "soldK": null, "regularMarketDayHigh": "42.65", "regularMarketDayLow": "41.90", "rowId": "2337.TW", "symbolName": "\u65fa\u5b8f", "volK": 19288, "inRankCount": 1}, {"change": "0.15", "changePercent": "+0.45%", "dayHigh": "33.31", "dayHighLimitDown": false, "dayHighLimitUp": false, "dayHighLowDiff": "0.16", "dayLow": "33.15", "dayLowLimitDown": false, "dayLowLimitUp": false, "limitDown": false, "limitUp": false, "name": "\u5143\u5927\u9ad8\u80a1\u606f", "previousClose": "33.03", "price": "33.18", "rank": "87", "symbol": "0056.TW", "turnoverK": "798363", "volume": "24017000", "previousLimitUp": false, "previousLimitDown": false, "previousChange": null, "previousChangePercent": null, "holdK": null, "holdPercent": null, "overboughtK": null, "oversoldK": null, "boughtK": null, "soldK": null, "regularMarketDayHigh": "33.31", "regularMarketDayLow": "33.15", "rowId": "0056.TW", "symbolName": "\u5143\u5927\u9ad8\u80a1\u606f", "volK": 24017, "prevRank": "91", "inRankCount": 3}, {"change": "0.10", "changePercent": "+0.28%", "dayHigh": "35.30", "dayHighLimitDown": false, "dayHighLimitUp": false, "dayHighLowDiff": "0.35", "dayLow": "34.95", "dayLowLimitDown": false, "dayLowLimitUp": false, "limitDown": false, "limitUp": false, "name": "\u5146\u8c50\u91d1", "previousClose": "35.10", "price": "35.20", "rank": "88", "symbol": "2886.TW", "turnoverK": "796343", "volume": "22655000", "previousLimitUp": false, "previousLimitDown": false, "previousChange": null, "previousChangePercent": null, "holdK": null, "holdPercent": null, "overboughtK": null, "oversoldK": null, "boughtK": null, "soldK": null, "regularMarketDayHigh": "35.30", "regularMarketDayLow": "34.95", "rowId": "2886.TW", "symbolName": "\u5146\u8c50\u91d1", "volK": 22655, "prevRank": "87", "inRankCount": 3}, {"change": "1.5", "changePercent": "+1.36%", "dayHigh": "115.0", "dayHighLimitDown": false, "dayHighLimitUp": false, "dayHighLowDiff": "3.50", "dayLow": "111.5", "dayLowLimitDown": false, "dayLowLimitUp": false, "limitDown": false, "limitUp": false, "name": "\u5bcc\u9f0e", "previousClose": "110.0", "price": "111.5", "rank": "89", "symbol": "8261.TW", "turnoverK": "755835", "volume": "6684000", "previousLimitUp": false, "previousLimitDown": false, "previousChange": null, "previousChangePercent": null, "holdK": null, "holdPercent": null, "overboughtK": null, "oversoldK": null, "boughtK": null, "soldK": null, "regularMarketDayHigh": "115.0", "regularMarketDayLow": "111.5", "rowId": "8261.TW", "symbolName": "\u5bcc\u9f0e", "volK": 6684, "prevRank": "73", "inRankCount": 2}, {"change": "2.0", "changePercent": "+0.72%", "dayHigh": "283.0", "dayHighLimitDown": false, "dayHighLimitUp": false, "dayHighLowDiff": "7.00", "dayLow": "276.0", "dayLowLimitDown": false, "dayLowLimitUp": false, "limitDown": false, "limitUp": false, "name": "\u53f0\u5149\u96fb", "previousClose": "278.0", "price": "280.0", "rank": "90", "symbol": "2383.TW", "turnoverK": "741387", "volume": "2648000", "previousLimitUp": false, "previousLimitDown": false, "previousChange": null, "previousChangePercent": null, "holdK": null, "holdPercent": null, "overboughtK": null, "oversoldK": null, "boughtK": null, "soldK": null, "regularMarketDayHigh": "283.0", "regularMarketDayLow": "276.0", "rowId": "2383.TW", "symbolName": "\u53f0\u5149\u96fb", "volK": 2648, "prevRank": "52", "inRankCount": 11}, {"change": "5", "changePercent": "+0.88%", "dayHigh": "581", "dayHighLimitDown": false, "dayHighLimitUp": false, "dayHighLowDiff": "11.00", "dayLow": "570", "dayLowLimitDown": false, "dayLowLimitUp": false, "limitDown": false, "limitUp": false, "name": "\u5275\u610f", "previousClose": "568", "price": "573", "rank": "91", "symbol": "3443.TW", "turnoverK": "741369", "volume": "1290000", "previousLimitUp": false, "previousLimitDown": false, "previousChange": null, "previousChangePercent": null, "holdK": null, "holdPercent": null, "overboughtK": null, "oversoldK": null, "boughtK": null, "soldK": null, "regularMarketDayHigh": "581", "regularMarketDayLow": "570", "rowId": "3443.TW", "symbolName": "\u5275\u610f", "volK": 1290, "prevRank": "65", "inRankCount": 6}, {"change": "-11.0", "changePercent": "-2.51%", "dayHigh": "454.0", "dayHighLimitDown": false, "dayHighLimitUp": false, "dayHighLowDiff": "26.00", "dayLow": "428.0", "dayLowLimitDown": false, "dayLowLimitUp": false, "limitDown": false, "limitUp": false, "name": "\u5065\u7b56", "previousClose": "439.0", "price": "428.0", "rank": "92", "symbol": "3653.TW", "turnoverK": "732186", "volume": "1675000", "previousLimitUp": false, "previousLimitDown": false, "previousChange": null, "previousChangePercent": null, "holdK": null, "holdPercent": null, "overboughtK": null, "oversoldK": null, "boughtK": null, "soldK": null, "regularMarketDayHigh": "454.0", "regularMarketDayLow": "428.0", "rowId": "3653.TW", "symbolName": "\u5065\u7b56", "volK": 1675, "prevRank": "94", "inRankCount": 4}, {"change": "55", "changePercent": "+3.43%", "dayHigh": "1695", "dayHighLimitDown": false, "dayHighLimitUp": false, "dayHighLowDiff": "60.00", "dayLow": "1635", "dayLowLimitDown": false, "dayLowLimitUp": false, "limitDown": false, "limitUp": false, "name": "\u5bcc\u90a6\u5a92", "previousClose": "1605", "price": "1660", "rank": "93", "symbol": "8454.TW", "turnoverK": "730790", "volume": "439000", "previousLimitUp": false, "previousLimitDown": false, "previousChange": null, "previousChangePercent": null, "holdK": null, "holdPercent": null, "overboughtK": null, "oversoldK": null, "boughtK": null, "soldK": null, "regularMarketDayHigh": "1695", "regularMarketDayLow": "1635", "rowId": "8454.TW", "symbolName": "\u5bcc\u90a6\u5a92", "volK": 439, "prevRank": "96", "inRankCount": 2}, {"change": "1.05", "changePercent": "+5.9%", "dayHigh": "19.30", "dayHighLimitDown": false, "dayHighLimitUp": false, "dayHighLowDiff": "1.50", "dayLow": "17.80", "dayLowLimitDown": false, "dayLowLimitUp": false, "limitDown": false, "limitUp": false, "name": "\u4e2d\u96fb", "previousClose": "17.80", "price": "18.85", "rank": "94", "symbol": "1611.TW", "turnoverK": "722973", "volume": "38740000", "previousLimitUp": false, "previousLimitDown": false, "previousChange": null, "previousChangePercent": null, "holdK": null, "holdPercent": null, "overboughtK": null, "oversoldK": null, "boughtK": null, "soldK": null, "regularMarketDayHigh": "19.30", "regularMarketDayLow": "17.80", "rowId": "1611.TW", "symbolName": "\u4e2d\u96fb", "volK": 38740, "inRankCount": 1}, {"change": "7", "changePercent": "+1.14%", "dayHigh": "626", "dayHighLimitDown": false, "dayHighLimitUp": false, "dayHighLowDiff": "11.00", "dayLow": "615", "dayLowLimitDown": false, "dayLowLimitUp": false, "limitDown": false, "limitUp": false, "name": "\u5112\u9d3b", "previousClose": "615", "price": "622", "rank": "95", "symbol": "1476.TW", "turnoverK": "705717", "volume": "1136000", "previousLimitUp": false, "previousLimitDown": false, "previousChange": null, "previousChangePercent": null, "holdK": null, "holdPercent": null, "overboughtK": null, "oversoldK": null, "boughtK": null, "soldK": null, "regularMarketDayHigh": "626", "regularMarketDayLow": "615", "rowId": "1476.TW", "symbolName": "\u5112\u9d3b", "volK": 1136, "prevRank": "74", "inRankCount": 2}, {"change": "0.20", "changePercent": "+0.56%", "dayHigh": "39.30", "dayHighLimitDown": false, "dayHighLimitUp": false, "dayHighLowDiff": "3.30", "dayLow": "36.00", "dayLowLimitDown": false, "dayLowLimitUp": false, "limitDown": false, "limitUp": false, "name": "\u6d77\u5149", "previousClose": "35.80", "price": "36.00", "rank": "96", "symbol": "2038.TW", "turnoverK": "697126", "volume": "18556000", "previousLimitUp": false, "previousLimitDown": false, "previousChange": null, "previousChangePercent": null, "holdK": null, "holdPercent": null, "overboughtK": null, "oversoldK": null, "boughtK": null, "soldK": null, "regularMarketDayHigh": "39.30", "regularMarketDayLow": "36.00", "rowId": "2038.TW", "symbolName": "\u6d77\u5149", "volK": 18556, "inRankCount": 1}, {"change": "-0.5", "changePercent": "-0.47%", "dayHigh": "107.5", "dayHighLimitDown": false, "dayHighLimitUp": false, "dayHighLowDiff": "3.50", "dayLow": "104.0", "dayLowLimitDown": false, "dayLowLimitUp": false, "limitDown": false, "limitUp": false, "name": "\u51f1\u7f8e", "previousClose": "105.5", "price": "105.0", "rank": "97", "symbol": "2375.TW", "turnoverK": "696592", "volume": "6601000", "previousLimitUp": false, "previousLimitDown": false, "previousChange": null, "previousChangePercent": null, "holdK": null, "holdPercent": null, "overboughtK": null, "oversoldK": null, "boughtK": null, "soldK": null, "regularMarketDayHigh": "107.5", "regularMarketDayLow": "104.0", "rowId": "2375.TW", "symbolName": "\u51f1\u7f8e", "volK": 6601, "prevRank": "32", "inRankCount": 11}, {"change": "-0.90", "changePercent": "-2.3%", "dayHigh": "39.90", "dayHighLimitDown": false, "dayHighLimitUp": false, "dayHighLowDiff": "1.85", "dayLow": "38.05", "dayLowLimitDown": false, "dayLowLimitUp": false, "limitDown": false, "limitUp": false, "name": "\u98db\u5b8f", "previousClose": "39.10", "price": "38.20", "rank": "98", "symbol": "2457.TW", "turnoverK": "677594", "volume": "17474000", "previousLimitUp": false, "previousLimitDown": false, "previousChange": null, "previousChangePercent": null, "holdK": null, "holdPercent": null, "overboughtK": null, "oversoldK": null, "boughtK": null, "soldK": null, "regularMarketDayHigh": "39.90", "regularMarketDayLow": "38.05", "rowId": "2457.TW", "symbolName": "\u98db\u5b8f", "volK": 17474, "prevRank": "56", "inRankCount": 2}, {"change": "15.5", "changePercent": "+7.43%", "dayHigh": "226.0", "dayHighLimitDown": false, "dayHighLimitUp": false, "dayHighLowDiff": "11.00", "dayLow": "215.0", "dayLowLimitDown": false, "dayLowLimitUp": false, "limitDown": false, "limitUp": false, "name": "\u8c50\u6cf0", "previousClose": "208.5", "price": "224.0", "rank": "99", "symbol": "9910.TW", "turnoverK": "676976", "volume": "3058000", "previousLimitUp": false, "previousLimitDown": false, "previousChange": null, "previousChangePercent": null, "holdK": null, "holdPercent": null, "overboughtK": null, "oversoldK": null, "boughtK": null, "soldK": null, "regularMarketDayHigh": "226.0", "regularMarketDayLow": "215.0", "rowId": "9910.TW", "symbolName": "\u8c50\u6cf0", "volK": 3058, "inRankCount": 1}, {"change": "0.05", "changePercent": "+0.31%", "dayHigh": "16.60", "dayHighLimitDown": false, "dayHighLimitUp": false, "dayHighLowDiff": "0.35", "dayLow": "16.25", "dayLowLimitDown": false, "dayLowLimitUp": false, "limitDown": false, "limitUp": false, "name": "\u5f69\u6676", "previousClose": "16.35", "price": "16.40", "rank": "100", "symbol": "6116.TW", "turnoverK": "673851", "volume": "41082000", "previousLimitUp": false, "previousLimitDown": false, "previousChange": null, "previousChangePercent": null, "holdK": null, "holdPercent": null, "overboughtK": null, "oversoldK": null, "boughtK": null, "soldK": null, "regularMarketDayHigh": "16.60", "regularMarketDayLow": "16.25", "rowId": "6116.TW", "symbolName": "\u5f69\u6676", "volK": 41082, "prevRank": "68", "inRankCount": 2}], "removed": [{"change": "-3.10", "changePercent": "-9.72%", "dayHigh": "32.95", "dayHighLimitDown": false, "dayHighLimitUp": false, "dayHighLowDiff": "4.15", "dayLow": "28.80", "dayLowLimitDown": false, "dayLowLimitUp": false, "limitDown": false, "limitUp": false, "name": "\u9f0e\u5143", "previousClose": "31.90", "price": "28.80", "rank": "30", "symbol": "2426.TW", "turnoverK": "2332539", "volume": "76233000", "previousLimitUp": false, "previousLimitDown": false, "previousChange": null, "previousChangePercent": null, "holdK": null, "holdPercent": null, "overboughtK": null, "oversoldK": null, "boughtK": null, "soldK": null, "regularMarketDayHigh": "32.95", "regularMarketDayLow": "28.80", "rowId": "2426.TW", "symbolName": "\u9f0e\u5143", "volK": 76233, "prevRank": "57", "inRankCount": 2}, {"change": "-5.0", "changePercent": "-2.96%", "dayHigh": "168.5", "dayHighLimitDown": false, "dayHighLimitUp": false, "dayHighLowDiff": "4.50", "dayLow": "164.0", "dayLowLimitDown": false, "dayLowLimitUp": false, "limitDown": false, "limitUp": false, "name": "\u83ef\u65b0\u79d1", "previousClose": "169.0", "price": "164.0", "rank": "57", "symbol": "2492.TW", "turnoverK": "1275383", "volume": "7721000", "previousLimitUp": false, "previousLimitDown": false, "previousChange": null, "previousChangePercent": null, "holdK": null, "holdPercent": null, "overboughtK": null, "oversoldK": null, "boughtK": null, "soldK": null, "regularMarketDayHigh": "168.5", "regularMarketDayLow": "164.0", "rowId": "2492.TW", "symbolName": "\u83ef\u65b0\u79d1", "volK": 7721, "inRankCount": 1}, {"change": "0.0", "changePercent": "0%", "dayHigh": "172.0", "dayHighLimitDown": false, "dayHighLimitUp": false, "dayHighLowDiff": "9.50", "dayLow": "162.5", "dayLowLimitDown": false, "dayLowLimitUp": false, "limitDown": false, "limitUp": false, "name": "\u9806\u5fb7", "previousClose": "163.5", "price": "163.5", "rank": "58", "symbol": "2351.TW", "turnoverK": "1251022", "volume": "7494000", "previousLimitUp": false, "previousLimitDown": false, "previousChange": null, "previousChangePercent": null, "holdK": null, "holdPercent": null, "overboughtK": null, "oversoldK": null, "boughtK": null, "soldK": null, "regularMarketDayHigh": "172.0", "regularMarketDayLow": "162.5", "rowId": "2351.TW", "symbolName": "\u9806\u5fb7", "volK": 7494, "inRankCount": 1}, {"change": "-0.40", "changePercent": "-0.93%", "dayHigh": "43.70", "dayHighLimitDown": false, "dayHighLimitUp": false, "dayHighLowDiff": "1.40", "dayLow": "42.30", "dayLowLimitDown": false, "dayLowLimitUp": false, "limitDown": false, "limitUp": false, "name": "\u83ef\u901a", "previousClose": "42.90", "price": "42.50", "rank": "63", "symbol": "2313.TW", "turnoverK": "1108534", "volume": "25810000", "previousLimitUp": false, "previousLimitDown": false, "previousChange": null, "previousChangePercent": null, "holdK": null, "holdPercent": null, "overboughtK": null, "oversoldK": null, "boughtK": null, "soldK": null, "regularMarketDayHigh": "43.70", "regularMarketDayLow": "42.30", "rowId": "2313.TW", "symbolName": "\u83ef\u901a", "volK": 25810, "prevRank": "65", "inRankCount": 2}, {"change": "-0.5", "changePercent": "-0.78%", "dayHigh": "66.7", "dayHighLimitDown": false, "dayHighLimitUp": false, "dayHighLowDiff": "4.40", "dayLow": "62.3", "dayLowLimitDown": false, "dayLowLimitUp": false, "limitDown": false, "limitUp": false, "name": "\u9245\u7965", "previousClose": "63.9", "price": "63.4", "rank": "66", "symbol": "2476.TW", "turnoverK": "1002891", "volume": "15489000", "previousLimitUp": false, "previousLimitDown": false, "previousChange": null, "previousChangePercent": null, "holdK": null, "holdPercent": null, "overboughtK": null, "oversoldK": null, "boughtK": null, "soldK": null, "regularMarketDayHigh": "66.7", "regularMarketDayLow": "62.3", "rowId": "2476.TW", "symbolName": "\u9245\u7965", "volK": 15489, "prevRank": "89", "inRankCount": 2}, {"change": "-4.2", "changePercent": "-4.18%", "dayHigh": "99.6", "dayHighLimitDown": false, "dayHighLimitUp": false, "dayHighLowDiff": "3.50", "dayLow": "96.1", "dayLowLimitDown": false, "dayLowLimitUp": false, "limitDown": false, "limitUp": false, "name": "\u7f8e\u6642", "previousClose": "100.5", "price": "96.3", "rank": "69", "symbol": "1795.TW", "turnoverK": "946885", "volume": "9690000", "previousLimitUp": false, "previousLimitDown": false, "previousChange": null, "previousChangePercent": null, "holdK": null, "holdPercent": null, "overboughtK": null, "oversoldK": null, "boughtK": null, "soldK": null, "regularMarketDayHigh": "99.6", "regularMarketDayLow": "96.1", "rowId": "1795.TW", "symbolName": "\u7f8e\u6642", "volK": 9690, "inRankCount": 1}, {"change": "3.5", "changePercent": "+1.36%", "dayHigh": "260.0", "dayHighLimitDown": false, "dayHighLimitUp": false, "dayHighLowDiff": "8.50", "dayLow": "251.5", "dayLowLimitDown": false, "dayLowLimitUp": false, "limitDown": false, "limitUp": false, "name": "\u4e2d\u79df-KY", "previousClose": "256.5", "price": "260.0", "rank": "75", "symbol": "5871.TW", "turnoverK": "859268", "volume": "3348000", "previousLimitUp": false, "previousLimitDown": false, "previousChange": null, "previousChangePercent": null, "holdK": null, "holdPercent": null, "overboughtK": null, "oversoldK": null, "boughtK": null, "soldK": null, "regularMarketDayHigh": "260.0", "regularMarketDayLow": "251.5", "rowId": "5871.TW", "symbolName": "\u4e2d\u79df-KY", "volK": 3348, "prevRank": "95", "inRankCount": 2}, {"change": "0.50", "changePercent": "+1.96%", "dayHigh": "26.10", "dayHighLimitDown": false, "dayHighLimitUp": false, "dayHighLowDiff": "0.60", "dayLow": "25.50", "dayLowLimitDown": false, "dayLowLimitUp": false, "limitDown": false, "limitUp": false, "name": "\u570b\u78a9", "previousClose": "25.45", "price": "25.95", "rank": "77", "symbol": "2406.TW", "turnoverK": "811102", "volume": "31361000", "previousLimitUp": false, "previousLimitDown": false, "previousChange": null, "previousChangePercent": null, "holdK": null, "holdPercent": null, "overboughtK": null, "oversoldK": null, "boughtK": null, "soldK": null, "regularMarketDayHigh": "26.10", "regularMarketDayLow": "25.50", "rowId": "2406.TW", "symbolName": "\u570b\u78a9", "volK": 31361, "prevRank": "67", "inRankCount": 4}, {"change": "-1.0", "changePercent": "-0.83%", "dayHigh": "124.5", "dayHighLimitDown": false, "dayHighLimitUp": false, "dayHighLowDiff": "4.50", "dayLow": "120.0", "dayLowLimitDown": false, "dayLowLimitUp": false, "limitDown": false, "limitUp": false, "name": "\u53f0\u8868\u79d1", "previousClose": "121.0", "price": "120.0", "rank": "79", "symbol": "6278.TW", "turnoverK": "802054", "volume": "6573000", "previousLimitUp": false, "previousLimitDown": false, "previousChange": null, "previousChangePercent": null, "holdK": null, "holdPercent": null, "overboughtK": null, "oversoldK": null, "boughtK": null, "soldK": null, "regularMarketDayHigh": "124.5", "regularMarketDayLow": "120.0", "rowId": "6278.TW", "symbolName": "\u53f0\u8868\u79d1", "volK": 6573, "prevRank": "91", "inRankCount": 2}, {"change": "0.1", "changePercent": "+0.16%", "dayHigh": "67.8", "dayHighLimitDown": false, "dayHighLimitUp": false, "dayHighLowDiff": "7.50", "dayLow": "60.3", "dayLowLimitDown": false, "dayLowLimitUp": false, "limitDown": false, "limitUp": false, "name": "\u8a6e\u6b23", "previousClose": "61.9", "price": "62.0", "rank": "80", "symbol": "6205.TW", "turnoverK": "796991", "volume": "12462000", "previousLimitUp": false, "previousLimitDown": false, "previousChange": null, "previousChangePercent": null, "holdK": null, "holdPercent": null, "overboughtK": null, "oversoldK": null, "boughtK": null, "soldK": null, "regularMarketDayHigh": "67.8", "regularMarketDayLow": "60.3", "rowId": "6205.TW", "symbolName": "\u8a6e\u6b23", "volK": 12462, "inRankCount": 1}, {"change": "-6.8", "changePercent": "-9.63%", "dayHigh": "72.4", "dayHighLimitDown": false, "dayHighLimitUp": false, "dayHighLowDiff": "8.60", "dayLow": "63.8", "dayLowLimitDown": false, "dayLowLimitUp": false, "limitDown": false, "limitUp": false, "name": "\u8fc5\u6770", "previousClose": "70.6", "price": "63.8", "rank": "82", "symbol": "6243.TW", "turnoverK": "785598", "volume": "11579000", "previousLimitUp": false, "previousLimitDown": false, "previousChange": null, "previousChangePercent": null, "holdK": null, "holdPercent": null, "overboughtK": null, "oversoldK": null, "boughtK": null, "soldK": null, "regularMarketDayHigh": "72.4", "regularMarketDayLow": "63.8", "rowId": "6243.TW", "symbolName": "\u8fc5\u6770", "volK": 11579, "prevRank": "49", "inRankCount": 3}, {"change": "1.90", "changePercent": "+4.23%", "dayHigh": "47.25", "dayHighLimitDown": false, "dayHighLimitUp": false, "dayHighLowDiff": "1.05", "dayLow": "46.20", "dayLowLimitDown": false, "dayLowLimitUp": false, "limitDown": false, "limitUp": false, "name": "\u81f3\u4e0a", "previousClose": "44.90", "price": "46.80", "rank": "84", "symbol": "8112.TW", "turnoverK": "752634", "volume": "16098000", "previousLimitUp": false, "previousLimitDown": false, "previousChange": null, "previousChangePercent": null, "holdK": null, "holdPercent": null, "overboughtK": null, "oversoldK": null, "boughtK": null, "soldK": null, "regularMarketDayHigh": "47.25", "regularMarketDayLow": "46.20", "rowId": "8112.TW", "symbolName": "\u81f3\u4e0a", "volK": 16098, "inRankCount": 1}, {"change": "-1.0", "changePercent": "-0.98%", "dayHigh": "103.0", "dayHighLimitDown": false, "dayHighLimitUp": false, "dayHighLowDiff": "3.00", "dayLow": "100.0", "dayLowLimitDown": false, "dayLowLimitUp": false, "limitDown": false, "limitUp": false, "name": "\u6676\u6280", "previousClose": "102.0", "price": "101.0", "rank": "85", "symbol": "3042.TW", "turnoverK": "751285", "volume": "7444000", "previousLimitUp": false, "previousLimitDown": false, "previousChange": null, "previousChangePercent": null, "holdK": null, "holdPercent": null, "overboughtK": null, "oversoldK": null, "boughtK": null, "soldK": null, "regularMarketDayHigh": "103.0", "regularMarketDayLow": "100.0", "rowId": "3042.TW", "symbolName": "\u6676\u6280", "volK": 7444, "prevRank": "63", "inRankCount": 2}, {"change": "-14", "changePercent": "-2.5%", "dayHigh": "569", "dayHighLimitDown": false, "dayHighLimitUp": false, "dayHighLowDiff": "27.00", "dayLow": "542", "dayLowLimitDown": false, "dayLowLimitUp": false, "limitDown": false, "limitUp": false, "name": "\u6676\u5fc3\u79d1", "previousClose": "560", "price": "546", "rank": "93", "symbol": "6533.TW", "turnoverK": "685818", "volume": "1241000", "previousLimitUp": false, "previousLimitDown": false, "previousChange": null, "previousChangePercent": null, "holdK": null, "holdPercent": null, "overboughtK": null, "oversoldK": null, "boughtK": null, "soldK": null, "regularMarketDayHigh": "569", "regularMarketDayLow": "542", "rowId": "6533.TW", "symbolName": "\u6676\u5fc3\u79d1", "volK": 1241, "prevRank": "69", "inRankCount": 21}, {"change": "-5.0", "changePercent": "-3.27%", "dayHigh": "159.5", "dayHighLimitDown": false, "dayHighLimitUp": false, "dayHighLowDiff": "11.50", "dayLow": "148.0", "dayLowLimitDown": false, "dayLowLimitUp": false, "limitDown": false, "limitUp": false, "name": "\u901a\u5609", "previousClose": "153.0", "price": "148.0", "rank": "97", "symbol": "3588.TW", "turnoverK": "674784", "volume": "4407000", "previousLimitUp": false, "previousLimitDown": false, "previousChange": null, "previousChangePercent": null, "holdK": null, "holdPercent": null, "overboughtK": null, "oversoldK": null, "boughtK": null, "soldK": null, "regularMarketDayHigh": "159.5", "regularMarketDayLow": "148.0", "rowId": "3588.TW", "symbolName": "\u901a\u5609", "volK": 4407, "inRankCount": 1}, {"change": "0.50", "changePercent": "+1.11%", "dayHigh": "45.75", "dayHighLimitDown": false, "dayHighLimitUp": false, "dayHighLowDiff": "0.75", "dayLow": "45.00", "dayLowLimitDown": false, "dayLowLimitUp": false, "limitDown": false, "limitUp": false, "name": "\u4eac\u5143\u96fb\u5b50", "previousClose": "44.95", "price": "45.45", "rank": "99", "symbol": "2449.TW", "turnoverK": "662962", "volume": "14625000", "previousLimitUp": false, "previousLimitDown": false, "previousChange": null, "previousChangePercent": null, "holdK": null, "holdPercent": null, "overboughtK": null, "oversoldK": null, "boughtK": null, "soldK": null, "regularMarketDayHigh": "45.75", "regularMarketDayLow": "45.00", "rowId": "2449.TW", "symbolName": "\u4eac\u5143\u96fb\u5b50", "volK": 14625, "inRankCount": 1}, {"change": "9.5", "changePercent": "+3.35%", "dayHigh": "294.0", "dayHighLimitDown": false, "dayHighLimitUp": false, "dayHighLowDiff": "13.50", "dayLow": "280.5", "dayLowLimitDown": false, "dayLowLimitUp": false, "limitDown": false, "limitUp": false, "name": "\u667a\u90a6", "previousClose": "283.5", "price": "293.0", "rank": "100", "symbol": "2345.TW", "turnoverK": "649110", "volume": "2258000", "previousLimitUp": false, "previousLimitDown": false, "previousChange": null, "previousChangePercent": null, "holdK": null, "holdPercent": null, "overboughtK": null, "oversoldK": null, "boughtK": null, "soldK": null, "regularMarketDayHigh": "294.0", "regularMarketDayLow": "280.5", "rowId": "2345.TW", "symbolName": "\u667a\u90a6", "volK": 2258, "inRankCount": 1}], "rankTime": "2021-12-08T14:00:57+08:00"}